Verilog/28_PidController/pidMotorControl/src/pidMotorControl.sv
module fpgaPidMotorControl (
    input logic sys_clk,
    input logic sys_rst_n,

    input logic sampleEnable,

    input logic signed [15:0] setpoint,
    input logic signed [15:0] measuredValue,

    input logic signed [15:0] kp,
    input logic signed [15:0] ki,
    input logic signed [15:0] kd,

    output logic signed [15:0] controlOutput,
    output logic outputValid
);

    logic signed [15:0] currentError;
    logic signed [15:0] previousError;
    logic signed [15:0] errorDelta;

    logic signed [31:0] integralAccumulator;

    logic signed [31:0] proportionalProduct;
    logic signed [47:0] integralProduct;
    logic signed [31:0] derivativeProduct;

    logic signed [31:0] proportionalTerm;
    logic signed [31:0] integralTerm;
    logic signed [31:0] derivativeTerm;

    logic signed [31:0] pidSum;

    assign currentError = setpoint - measuredValue;
    assign errorDelta = currentError - previousError;

    // Q8.8 * Q8.8 = Q16.16
    assign proportionalProduct = currentError * kp;

    // integralAccumulator is 32-bit Q24.8
    // Multiplying by Q8.8 gives Q32.16
    assign integralProduct = integralAccumulator * ki;

    // Q8.8 * Q8.8 = Q16.16
    assign derivativeProduct = errorDelta * kd;

    // Shift right by 8 to convert Q16.16 back to Q24.8 / Q8.8 scale
    assign proportionalTerm = proportionalProduct >>> 8;
    assign integralTerm = integralProduct >>> 8;
    assign derivativeTerm = derivativeProduct >>> 8;

    assign pidSum = proportionalTerm + integralTerm + derivativeTerm;

    function automatic logic signed [15:0] saturate16(input logic signed [31:0] value);
        begin
            if (value > 32'sd32767) begin
                saturate16 = 16'sh7FFF;
            end else if (value < -32'sd32768) begin
                saturate16 = 16'sh8000;
            end else begin
                saturate16 = 16'(value);
            end
        end
    endfunction

    always_ff @(posedge sys_clk or negedge sys_rst_n) begin
        if (!sys_rst_n) begin
            previousError <= 16'sd0;
            integralAccumulator <= 32'sd0;
            controlOutput <= 16'sd0;
            outputValid <= 1'b0;
        end else begin
            outputValid <= 1'b0;

            if (sampleEnable) begin
                integralAccumulator <= integralAccumulator + currentError;
                previousError <= currentError;
                controlOutput <= saturate16(pidSum);

                outputValid <= 1'b1;
            end
        end
    end

endmodule

Verilog/28_PidController/sim/tb_pidMotorControl.sv
`timescale 1ns/1ps

module tb_pidMotorControl;

    logic sys_clk;
    logic sys_rst_n;

    logic sampleEnable;

    logic signed [15:0] setpoint;
    logic signed [15:0] measuredValue;

    logic signed [15:0] kp;
    logic signed [15:0] ki;
    logic signed [15:0] kd;

    logic signed [15:0] controlOutput;
    logic outputValid;

    fpgaPidMotorControl dut (
        .sys_clk(sys_clk),
        .sys_rst_n(sys_rst_n),

        .sampleEnable(sampleEnable),

        .setpoint(setpoint),
        .measuredValue(measuredValue),

        .kp(kp),
        .ki(ki),
        .kd(kd),

        .controlOutput(controlOutput),
        .outputValid(outputValid)
    );

    initial begin
        sys_clk = 1'b0;
        forever #18.518 sys_clk = ~sys_clk; // 27 MHz clock
    end

    task applySample(input logic signed [15:0] newMeasuredValue);
        begin
            @(negedge sys_clk);
            measuredValue = newMeasuredValue;
            sampleEnable = 1'b1;

            @(negedge sys_clk);
            sampleEnable = 1'b0;

            wait (outputValid == 1'b1);
            @(posedge sys_clk);

            $display("setpoint=%0d measured=%0d error=%0d output=%0d hex=%04h", setpoint, measuredValue, dut.currentError, controlOutput, controlOutput);
        end
    endtask

    initial begin
        $dumpfile("sim/tb_pidMotorControl.vcd");
        $dumpvars(0, tb_pidMotorControl);

        sys_rst_n = 1'b0;

        sampleEnable = 1'b0;

        setpoint = 16'sd0;
        measuredValue = 16'sd0;

        kp = 16'sd0;
        ki = 16'sd0;
        kd = 16'sd0;

        #200;
        sys_rst_n = 1'b1;

        // Gains: kp = 1.0, ki = 0.25, kd = 0.5
        kp = 16'sh0100;
        ki = 16'sh0040;
        kd = 16'sh0080;

        // Target is 10.0 in Q8.8
        setpoint = 16'sh0A00;

        // Simulated measured values approach setpoint: 0.0, 2.0, 5.0, 8.0, 9.0, 10.0, 11.0
        // As measured value approaches setpoint, error gets smaller
        // When measured value exceeds setpoint, error becomes negative

        applySample(16'sh0000); // measured = 0.0
        applySample(16'sh0200); // measured = 2.0
        applySample(16'sh0500); // measured = 5.0
        applySample(16'sh0800); // measured = 8.0
        applySample(16'sh0900); // measured = 9.0
        applySample(16'sh0A00); // measured = 10.0
        applySample(16'sh0B00); // measured = 11.0

        // Saturation test
        kp = 16'sh7F00;
        ki = 16'sd0;
        kd = 16'sd0;
        setpoint = 16'sh7F00;
        measuredValue = -16'sh7F00;

        applySample(measuredValue);

        repeat (6) @(posedge sys_clk);

        $finish;
    end

endmodule

Verilog/28_PidController/sim/tb_pidMotorControl.vcd
$date
	Sat Jul 11 13:29:36 2026
$end
$version
	Icarus Verilog
$end
$timescale
	1ps
$end
$scope module tb_pidMotorControl $end
$var wire 1 ! outputValid $end
$var wire 16 " controlOutput [15:0] $end
$var reg 16 # kd [15:0] $end
$var reg 16 $ ki [15:0] $end
$var reg 16 % kp [15:0] $end
$var reg 16 & measuredValue [15:0] $end
$var reg 1 ' sampleEnable $end
$var reg 16 ( setpoint [15:0] $end
$var reg 1 ) sys_clk $end
$var reg 1 * sys_rst_n $end
$scope module dut $end
$var wire 16 + kd [15:0] $end
$var wire 16 , ki [15:0] $end
$var wire 16 - kp [15:0] $end
$var wire 16 . measuredValue [15:0] $end
$var wire 1 ' sampleEnable $end
$var wire 16 / setpoint [15:0] $end
$var wire 1 ) sys_clk $end
$var wire 1 * sys_rst_n $end
$var wire 32 0 proportionalTerm [31:0] $end
$var wire 32 1 proportionalProduct [31:0] $end
$var wire 32 2 pidSum [31:0] $end
$var wire 32 3 integralTerm [31:0] $end
$var wire 48 4 integralProduct [47:0] $end
$var wire 16 5 errorDelta [15:0] $end
$var wire 32 6 derivativeTerm [31:0] $end
$var wire 32 7 derivativeProduct [31:0] $end
$var wire 16 8 currentError [15:0] $end
$var reg 16 9 controlOutput [15:0] $end
$var reg 32 : integralAccumulator [31:0] $end
$var reg 1 ! outputValid $end
$var reg 16 ; previousError [15:0] $end
$scope function saturate16 $end
$upscope $end
$upscope $end
$scope task applySample $end
$var reg 16 < newMeasuredValue [15:0] $end
$upscope $end
$upscope $end
$enddefinitions $end
$comment Show the parameter values. $end
$dumpall
$end
#0
$dumpvars
bx <
b0 ;
b0 :
b0 9
b0 8
b0 7
b0 6
b0 5
b0 4
b0 3
b0 2
b0 1
b0 0
b0 /
b0 .
b0 -
b0 ,
b0 +
0*
0)
b0 (
0'
b0 &
b0 %
b0 $
b0 #
b0 "
0!
$end
#18518
1)
#37036
0)
#55554
1)
#74072
0)
#92590
1)
#111108
0)
#129626
1)
#148144
0)
#166662
1)
#185180
0)
#200000
b10100000000 6
b111100000000 2
b101000000000 0
b0 <
b1010000000000000000 7
b101000000000 5
b10100000000000000000 1
b101000000000 8
b101000000000 (
b101000000000 /
b10000000 #
b10000000 +
b1000000 $
b1000000 ,
b100000000 %
b100000000 -
1*
#203698
1)
#222216
1'
0)
#240734
b1010000000 3
b110010000000 2
b0 6
1!
b111100000000 "
b111100000000 9
b0 7
b0 5
b101000000000 ;
b101000000000000000 4
b101000000000 :
1)
#259252
0'
0)
#277770
0!
b1000000000 <
1)
#296288
b11111111111111111111111100000000 6
b100110000000 2
b100000000000 0
1'
b11111111111111110000000000000000 7
b1111111000000000 5
b10000000000000000000 1
b100000000000 8
b1000000000 &
b1000000000 .
0)
#314806
b10010000000 3
b110010000000 2
b0 6
1!
b100110000000 "
b100110000000 9
b0 7
b0 5
b100000000000 ;
b1001000000000000000 4
b1001000000000 :
1)
#333324
0'
0)
#351842
0!
b10100000000 <
1)
#370360
b11111111111111111111111010000000 6
b100000000000 2
b10100000000 0
1'
b11111111111111101000000000000000 7
b1111110100000000 5
b1010000000000000000 1
b10100000000 8
b10100000000 &
b10100000000 .
0)
#388878
b10111000000 3
b101011000000 2
b0 6
1!
b100000000000 "
b100000000000 9
b0 7
b0 5
b10100000000 ;
b1011100000000000000 4
b1011100000000 :
1)
#407396
0'
0)
#425914
0!
b100000000000 <
1)
#444432
b11111111111111111111111010000000 6
b11001000000 2
b1000000000 0
1'
b11111111111111101000000000000000 7
b1111110100000000 5
b100000000000000000 1
b1000000000 8
b100000000000 &
b100000000000 .
0)
#462950
b11001000000 3
b100001000000 2
b0 6
1!
b11001000000 "
b11001000000 9
b0 7
b0 5
b1000000000 ;
b1100100000000000000 4
b1100100000000 :
1)
#481468
0'
0)
#499986
0!
b100100000000 <
1)
#518504
b11111111111111111111111110000000 6
b11011000000 2
b100000000 0
1'
b11111111111111111000000000000000 7
b1111111100000000 5
b10000000000000000 1
b100000000 8
b100100000000 &
b100100000000 .
0)
#537022
b11010000000 3
b11110000000 2
b0 6
1!
b11011000000 "
b11011000000 9
b0 7
b0 5
b100000000 ;
b1101000000000000000 4
b1101000000000 :
1)
#555540
0'
0)
#574058
0!
b101000000000 <
1)
#592576
b11111111111111111111111110000000 6
b11000000000 2
b0 0
1'
b11111111111111111000000000000000 7
b1111111100000000 5
b0 1
b0 8
b101000000000 &
b101000000000 .
0)
#611094
b11010000000 2
b0 6
1!
b11000000000 "
b11000000000 9
b0 7
b0 5
b0 ;
1)
#629612
0'
0)
#648130
0!
b101100000000 <
1)
#666648
b11111111111111111111111110000000 6
b10100000000 2
b11111111111111111111111100000000 0
1'
b11111111111111111000000000000000 7
b1111111100000000 5
b11111111111111110000000000000000 1
b1111111100000000 8
b101100000000 &
b101100000000 .
0)
#685166
b11001000000 3
b10101000000 2
b0 6
1!
b10100000000 "
b10100000000 9
b0 7
b0 5
b1111111100000000 ;
b1100100000000000000 4
b1100100000000 :
1)
#703684
0'
0)
#722202
0!
b0 3
b11111111111111110000001000000000 2
b11111111111111110000001000000000 0
b1000000100000000 <
b1000000100000000 &
b1000000100000000 .
b1111111100000000 5
b1111111000000000 8
b111111100000000 (
b111111100000000 /
b0 #
b0 +
b0 4
b0 $
b0 ,
b11111111000000100000000000000000 1
b111111100000000 %
b111111100000000 -
1)
#740720
1'
0)
#759238
1!
b1000000000000000 "
b1000000000000000 9
b0 5
b1111111000000000 ;
b1011100000000 :
1)
#777756
0'
0)
#796274
0!
1)
