15_PipelinedMultiplier/pipelinedMultiplier/src/pipelinedMultiplier.sv
// Process is done in 3 seperate but short clock cyles instead of 1 long clock cyle
// Timing is improved, but output arrives with latency

module pipelinedMultiplier (
    input logic sys_clk,
    input logic sys_rst_n,

    input logic inputValid,
    input logic signed [7:0] a,
    input logic signed [7:0] b,

    output logic outputValid,
    output logic signed [7:0] result
);

    localparam logic signed [15:0] MAX_Q4_4 = 16'sd127;
    localparam logic signed [15:0] MIN_Q4_4 = -16'sd128;

    logic stage1Valid;
    logic signed [7:0] stage1A;
    logic signed [7:0] stage1B;

    // Raw product Q8.8
    logic stage2Valid;
    logic signed [15:0] rawProduct;
    
    // Q8.8 -> Q4.4
    logic stage3Valid;
    logic signed [15:0] scaledProduct;

    // Saturation
    always_ff @(posedge sys_clk or negedge sys_rst_n) begin
        if (!sys_rst_n) begin
            stage1Valid <= 1'b0;
            stage1A <= 8'sd0;
            stage1B <= 8'sd0;

            stage2Valid <= 1'b0;
            rawProduct <= 16'sd0;

            stage3Valid <= 1'b0;
            scaledProduct <= 16'sd0;

            outputValid <= 1'b0;
            result <= 8'sd0;
        end else begin
            // Capture inputs
            stage1Valid <= inputValid;
            stage1A <= a;
            stage1B <= b;

            // Multiply
            stage2Valid <= stage1Valid;
            rawProduct <= stage1A * stage1B;
            
            // Scale back to Q4.4
            stage3Valid <= stage2Valid;
            scaledProduct <= rawProduct >>> 4;  // Arithmetic shift to preserve sign for negatives

            // Saturate and output
            outputValid <= stage3Valid;

            if (scaledProduct > MAX_Q4_4) begin
                result <= 8'sh7F;
            end else if (scaledProduct < MIN_Q4_4) begin
                result <= 8'sh80;
            end else begin
                result <= 8'(scaledProduct); // To fix Icarus Verilog warning
            end
        end
    end

endmodule

Verilog/15_PipelinedMultiplier/sim/tb_pipelinedMultiplier.sv
`timescale 1ns/1ps

module tb_pipelinedMultiplier;

    logic sys_clk;
    logic sys_rst_n;

    logic inputValid;
    logic signed [7:0] a;
    logic signed [7:0] b;

    logic outputValid;
    logic signed [7:0] result;

    pipelinedMultiplier dut (
        .sys_clk(sys_clk),
        .sys_rst_n(sys_rst_n),
        .inputValid(inputValid),
        .a(a),
        .b(b),
        .outputValid(outputValid),
        .result(result)
    );

    initial begin
        sys_clk = 1'b0;
        forever #18.518 sys_clk = ~sys_clk; // 27 MHz clock
    end

    // Drive one valid multiplication input for one clock cycle.
    // Inputs are changed on the falling edge so they are stable before the DUT samples them on the next rising edge.
    task sendMultiply(input logic signed [7:0] inputA, input logic signed [7:0] inputB); begin
            @(negedge sys_clk);
            a = inputA;
            b = inputB;
            inputValid = 1'b1;

            @(negedge sys_clk);
            inputValid = 1'b0;
            a = 8'sd0;
            b = 8'sd0;
        end
    endtask

    initial begin
        $dumpfile("sim/tb_pipelinedMultiplier.vcd");
        $dumpvars(0, tb_pipelinedMultiplier);

        sys_rst_n = 1'b0;
        inputValid = 1'b0;
        a = 8'sd0;
        b = 8'sd0;

        #200;
        sys_rst_n = 1'b1;

        // 2.0 * 2.0 = 4.0
        // 8'sh20 * 8'sh20 -> 8'sh40
        sendMultiply(8'sh20, 8'sh20);

        // 7.0 * 2.0 = 14.0, too large for Q4.4
        // Saturates to +7.9375 = 8'sh7F
        sendMultiply(8'sh70, 8'sh20);

        // -7.0 * 2.0 = -14.0, too small for Q4.4
        // Saturates to -8.0 = 8'sh80
        sendMultiply(8'sh90, 8'sh20);

        // 1.5 * 2.0 = 3.0
        // 8'sh18 * 8'sh20 -> 8'sh30
        sendMultiply(8'sh18, 8'sh20);

        // 0.5 * 0.5 = 0.25
        // 8'sh08 * 8'sh08 -> 8'sh04
        sendMultiply(8'sh08, 8'sh08);

        // Let the final pipeline result drain out, 8 is a safe margin
        repeat (8) @(posedge sys_clk); // Wait for 8 @(posedge sys_clk);

        $finish;
    end

endmodule

Verilog/15_PipelinedMultiplier/sim/tb_pipelinedMultiplier.vcd
$date
	Tue Jun 30 01:13:45 2026
$end
$version
	Icarus Verilog
$end
$timescale
	1ps
$end
$scope module tb_pipelinedMultiplier $end
$var wire 8 ! result [7:0] $end
$var wire 1 " outputValid $end
$var reg 8 # a [7:0] $end
$var reg 8 $ b [7:0] $end
$var reg 1 % inputValid $end
$var reg 1 & sys_clk $end
$var reg 1 ' sys_rst_n $end
$scope module dut $end
$var wire 8 ( a [7:0] $end
$var wire 8 ) b [7:0] $end
$var wire 1 % inputValid $end
$var wire 1 & sys_clk $end
$var wire 1 ' sys_rst_n $end
$var parameter 16 * MAX_Q4_4 $end
$var parameter 16 + MIN_Q4_4 $end
$var reg 1 " outputValid $end
$var reg 16 , rawProduct [15:0] $end
$var reg 8 - result [7:0] $end
$var reg 16 . scaledProduct [15:0] $end
$var reg 8 / stage1A [7:0] $end
$var reg 8 0 stage1B [7:0] $end
$var reg 1 1 stage1Valid $end
$var reg 1 2 stage2Valid $end
$var reg 1 3 stage3Valid $end
$upscope $end
$scope task sendMultiply $end
$var reg 8 4 inputA [7:0] $end
$var reg 8 5 inputB [7:0] $end
$upscope $end
$upscope $end
$enddefinitions $end
$comment Show the parameter values. $end
$dumpall
b1111111110000000 +
b1111111 *
$end
#0
$dumpvars
bx 5
bx 4
03
02
01
b0 0
b0 /
b0 .
b0 -
b0 ,
b0 )
b0 (
0'
0&
0%
b0 $
b0 #
0"
b0 !
$end
#18518
1&
#37036
0&
#55554
1&
#74072
0&
#92590
1&
#111108
0&
#129626
1&
#148144
0&
#166662
1&
#185180
0&
#200000
b100000 5
b100000 4
1'
#203698
1&
#222216
1%
b100000 $
b100000 )
b100000 #
b100000 (
0&
#240734
b100000 0
b100000 /
11
1&
#259252
b1110000 4
b0 $
b0 )
b0 #
b0 (
0%
0&
#277770
b10000000000 ,
12
b0 0
b0 /
01
1&
#296288
1%
b100000 $
b100000 )
b1110000 #
b1110000 (
0&
#314806
b1000000 .
13
b0 ,
02
b100000 0
b1110000 /
11
1&
#333324
b10010000 4
b0 $
b0 )
b0 #
b0 (
0%
0&
#351842
b1000000 !
b1000000 -
1"
b0 .
03
b111000000000 ,
12
b0 0
b0 /
01
1&
#370360
1%
b100000 $
b100000 )
b10010000 #
b10010000 (
0&
#388878
b0 !
b0 -
0"
b11100000 .
13
b0 ,
02
b100000 0
b10010000 /
11
1&
#407396
b11000 4
b0 $
b0 )
b0 #
b0 (
0%
0&
#425914
b1111111 !
b1111111 -
1"
b0 .
03
b1111001000000000 ,
12
b0 0
b0 /
01
1&
#444432
1%
b100000 $
b100000 )
b11000 #
b11000 (
0&
#462950
b0 !
b0 -
0"
b1111111100100000 .
13
b0 ,
02
b100000 0
b11000 /
11
1&
#481468
b1000 5
b1000 4
b0 $
b0 )
b0 #
b0 (
0%
0&
#499986
b10000000 !
b10000000 -
1"
b0 .
03
b1100000000 ,
12
b0 0
b0 /
01
1&
#518504
1%
b1000 $
b1000 )
b1000 #
b1000 (
0&
#537022
b0 !
b0 -
0"
b110000 .
13
b0 ,
02
b1000 0
b1000 /
11
1&
#555540
b0 $
b0 )
b0 #
b0 (
0%
0&
#574058
b110000 !
b110000 -
1"
b0 .
03
b1000000 ,
12
b0 0
b0 /
01
1&
#592576
0&
#611094
b0 !
b0 -
0"
b100 .
13
b0 ,
02
1&
#629612
0&
#648130
b100 !
b100 -
1"
b0 .
03
1&
#666648
0&
#685166
b0 !
b0 -
0"
1&
