Verilog/08_QuadratureDecoder/quadratureDecoder/src/quadratureDecoder.sv
module quadratureDecoder (
    input logic sys_clk,
    input logic sys_rst_n,
    input logic quad_a,
    input logic quad_b,
    output logic [4:0] led
);

    // Synchronizer registers
    // Each signal gets its own two-flop synchronizer.
    logic quadA_sync0;
    logic quadA_sync1;
    logic quadB_sync0;
    logic quadB_sync1;

    // Previous and current quadrature state.
    //   bit 1 = A
    //   bit 0 = B
    logic [1:0] quadState;
    logic [1:0] quadStatePrev;

    // Signed position counter.
    // It increments for one direction and decrements for the other.
    // LEDs show the low 6 bits of the position.
    logic [4:0] positionCounter;

    always_ff @(posedge sys_clk or negedge sys_rst_n) begin
        if (!sys_rst_n) begin
            quadA_sync0     <= 1'b0;
            quadA_sync1     <= 1'b0;
            quadB_sync0     <= 1'b0;
            quadB_sync1     <= 1'b0;
            quadState       <= 2'b00;
            quadStatePrev   <= 2'b00;
            positionCounter <= 6'd0;
        end else begin
            // Synchronize external quadrature inputs
            quadA_sync0 <= quad_a;
            quadA_sync1 <= quadA_sync0;
            quadB_sync0 <= quad_b;
            quadB_sync1 <= quadB_sync0;

            // Store previous state and sample current synchronized state
            quadStatePrev <= quadState;
            quadState     <= {quadA_sync1, quadB_sync1};

            // 3. Decode quadrature transition
            // Valid clockwise sequence example:
            //   00 -> 01 -> 11 -> 10 -> 00
            // Valid counterclockwise sequence example:
            //   00 -> 10 -> 11 -> 01 -> 00
            // Invalid transitions, such as 00 -> 11, are ignored.
            case ({quadStatePrev, quadState})
                // Forward transitions
                4'b0001,
                4'b0111,
                4'b1110,
                4'b1000: begin
                    positionCounter <= positionCounter + 1'b1;
                end

                // Reverse transitions
                4'b0010,
                4'b1011,
                4'b1101,
                4'b0100: begin
                    positionCounter <= positionCounter - 1'b1;
                end

                // No movement or invalid transition
                default: begin
                    positionCounter <= positionCounter;
                end
            endcase
        end
    end

    assign led = ~positionCounter;

endmodule

8_QuadratureDecoder/sim/tb_quadratureDecoder.sv
`timescale 1ns/1ps

module tb_quadratureDecoder;

    logic sys_clk;
    logic sys_rst_n;
    logic quad_a;
    logic quad_b;
    logic [5:0] led;

    quadratureDecoder dut (
        .sys_clk(sys_clk),
        .sys_rst_n(sys_rst_n),
        .quad_a(quad_a),
        .quad_b(quad_b),
        .led(led)
    );

    initial begin
        sys_clk = 1'b0;
        forever #18.518 sys_clk = ~sys_clk;   // 27 MHz
    end

    task stepQuadrature(input logic a, input logic b);
        begin
            quad_a = a;
            quad_b = b;
            #10_000;
        end
    endtask

    initial begin
        sys_rst_n = 1'b0;
        quad_a = 1'b0;
        quad_b = 1'b0;

        #200;
        sys_rst_n = 1'b1;

        // Forward: 00 -> 01 -> 11 -> 10 -> 00
        stepQuadrature(1'b0, 1'b1);
        stepQuadrature(1'b1, 1'b1);
        stepQuadrature(1'b1, 1'b0);
        stepQuadrature(1'b0, 1'b0);

        stepQuadrature(1'b0, 1'b1);
        stepQuadrature(1'b1, 1'b1);
        stepQuadrature(1'b1, 1'b0);
        stepQuadrature(1'b0, 1'b0);

        // Reverse: 00 -> 10 -> 11 -> 01 -> 00
        stepQuadrature(1'b1, 1'b0);
        stepQuadrature(1'b1, 1'b1);
        stepQuadrature(1'b0, 1'b1);
        stepQuadrature(1'b0, 1'b0);

        #50_000;
        $finish;
    end

    initial begin
        $dumpfile("tb_quadratureDecoder.vcd");
        $dumpvars(0, tb_quadratureDecoder);
    end

endmodule

Verilog/08_QuadratureDecoder/sim/tb_quadratureDecoder.vcd
$date
	Sun Jun 28 17:49:22 2026
$end
$version
	Icarus Verilog
$end
$timescale
	1ps
$end
$scope module tb_quadratureDecoder $end
$var wire 6 ! led [5:0] $end
$var reg 1 " quad_a $end
$var reg 1 # quad_b $end
$var reg 1 $ sys_clk $end
$var reg 1 % sys_rst_n $end
$scope module dut $end
$var wire 5 & led [4:0] $end
$var wire 1 " quad_a $end
$var wire 1 # quad_b $end
$var wire 1 $ sys_clk $end
$var wire 1 % sys_rst_n $end
$var reg 5 ' positionCounter [4:0] $end
$var reg 1 ( quadA_sync0 $end
$var reg 1 ) quadA_sync1 $end
$var reg 1 * quadB_sync0 $end
$var reg 1 + quadB_sync1 $end
$var reg 2 , quadState [1:0] $end
$var reg 2 - quadStatePrev [1:0] $end
$upscope $end
$scope task stepQuadrature $end
$var reg 1 . a $end
$var reg 1 / b $end
$upscope $end
$upscope $end
$enddefinitions $end
$comment Show the parameter values. $end
$dumpall
$end
#0
$dumpvars
x/
x.
b0 -
b0 ,
0+
0*
0)
0(
b0 '
b11111 &
0%
0$
0#
0"
b11111 !
$end
#18518
1$
#37036
0$
#55554
1$
#74072
0$
#92590
1$
#111108
0$
#129626
1$
#148144
0$
#166662
1$
#185180
0$
#200000
1#
1/
0.
1%
#203698
1*
1$
#222216
0$
#240734
1+
1$
#259252
0$
#277770
b1 ,
1$
#296288
0$
#314806
b11110 !
b11110 &
b1 '
b1 -
1$
#333324
0$
#351842
1$
#370360
0$
#388878
1$
#407396
0$
#425914
1$
#444432
0$
#462950
1$
#481468
0$
#499986
1$
#518504
0$
#537022
1$
#555540
0$
#574058
1$
#592576
0$
#611094
1$
#629612
0$
#648130
1$
#666648
0$
#685166
1$
#703684
0$
#722202
1$
#740720
0$
#759238
1$
#777756
0$
#796274
1$
#814792
0$
#833310
1$
#851828
0$
#870346
1$
#888864
0$
#907382
1$
#925900
0$
#944418
1$
#962936
0$
#981454
1$
#999972
0$
#1018490
1$
#1037008
0$
#1055526
1$
#1074044
0$
#1092562
1$
#1111080
0$
#1129598
1$
#1148116
0$
#1166634
1$
#1185152
0$
#1203670
1$
#1222188
0$
#1240706
1$
#1259224
0$
#1277742
1$
#1296260
0$
#1314778
1$
#1333296
0$
#1351814
1$
#1370332
0$
#1388850
1$
#1407368
0$
#1425886
1$
#1444404
0$
#1462922
1$
#1481440
0$
#1499958
1$
#1518476
0$
#1536994
1$
#1555512
0$
#1574030
1$
#1592548
0$
#1611066
1$
#1629584
0$
#1648102
1$
#1666620
0$
#1685138
1$
#1703656
0$
#1722174
1$
#1740692
0$
#1759210
1$
#1777728
0$
#1796246
1$
#1814764
0$
#1833282
1$
#1851800
0$
#1870318
1$
#1888836
0$
#1907354
1$
#1925872
0$
#1944390
1$
#1962908
0$
#1981426
1$
#1999944
0$
#2018462
1$
#2036980
0$
#2055498
1$
#2074016
0$
#2092534
1$
#2111052
0$
#2129570
1$
#2148088
0$
#2166606
1$
#2185124
0$
#2203642
1$
#2222160
0$
#2240678
1$
#2259196
0$
#2277714
1$
#2296232
0$
#2314750
1$
#2333268
0$
#2351786
1$
#2370304
0$
#2388822
1$
#2407340
0$
#2425858
1$
#2444376
0$
#2462894
1$
#2481412
0$
#2499930
1$
#2518448
0$
#2536966
1$
#2555484
0$
#2574002
1$
#2592520
0$
#2611038
1$
#2629556
0$
#2648074
1$
#2666592
0$
#2685110
1$
#2703628
0$
#2722146
1$
#2740664
0$
#2759182
1$
#2777700
0$
#2796218
1$
#2814736
0$
#2833254
1$
#2851772
0$
#2870290
1$
#2888808
0$
#2907326
1$
#2925844
0$
#2944362
1$
#2962880
0$
#2981398
1$
#2999916
0$
#3018434
1$
#3036952
0$
#3055470
1$
#3073988
0$
#3092506
1$
#3111024
0$
#3129542
1$
#3148060
0$
#3166578
1$
#3185096
0$
#3203614
1$
#3222132
0$
#3240650
1$
#3259168
0$
#3277686
1$
#3296204
0$
#3314722
1$
#3333240
0$
#3351758
1$
#3370276
0$
#3388794
1$
#3407312
0$
#3425830
1$
#3444348
0$
#3462866
1$
#3481384
0$
#3499902
1$
#3518420
0$
#3536938
1$
#3555456
0$
#3573974
1$
#3592492
0$
#3611010
1$
#3629528
0$
#3648046
1$
#3666564
0$
#3685082
1$
#3703600
0$
#3722118
1$
#3740636
0$
#3759154
1$
#3777672
0$
#3796190
1$
#3814708
0$
#3833226
1$
#3851744
0$
#3870262
1$
#3888780
0$
#3907298
1$
#3925816
0$
#3944334
1$
#3962852
0$
#3981370
1$
#3999888
0$
#4018406
1$
#4036924
0$
#4055442
1$
#4073960
0$
#4092478
1$
#4110996
0$
#4129514
1$
#4148032
0$
#4166550
1$
#4185068
0$
#4203586
1$
#4222104
0$
#4240622
1$
#4259140
0$
#4277658
1$
#4296176
0$
#4314694
1$
#4333212
0$
#4351730
1$
#4370248
0$
#4388766
1$
#4407284
0$
#4425802
1$
#4444320
0$
#4462838
1$
#4481356
0$
#4499874
1$
#4518392
0$
#4536910
1$
#4555428
0$
#4573946
1$
#4592464
0$
#4610982
1$
#4629500
0$
#4648018
1$
#4666536
0$
#4685054
1$
#4703572
0$
#4722090
1$
#4740608
0$
#4759126
1$
#4777644
0$
#4796162
1$
#4814680
0$
#4833198
1$
#4851716
0$
#4870234
1$
#4888752
0$
#4907270
1$
#4925788
0$
#4944306
1$
#4962824
0$
#4981342
1$
#4999860
0$
#5018378
1$
#5036896
0$
#5055414
1$
#5073932
0$
#5092450
1$
#5110968
0$
#5129486
1$
#5148004
0$
#5166522
1$
#5185040
0$
#5203558
1$
#5222076
0$
#5240594
1$
#5259112
0$
#5277630
1$
#5296148
0$
#5314666
1$
#5333184
0$
#5351702
1$
#5370220
0$
#5388738
1$
#5407256
0$
#5425774
1$
#5444292
0$
#5462810
1$
#5481328
0$
#5499846
1$
#5518364
0$
#5536882
1$
#5555400
0$
#5573918
1$
#5592436
0$
#5610954
1$
#5629472
0$
#5647990
1$
#5666508
0$
#5685026
1$
#5703544
0$
#5722062
1$
#5740580
0$
#5759098
1$
#5777616
0$
#5796134
1$
#5814652
0$
#5833170
1$
#5851688
0$
#5870206
1$
#5888724
0$
#5907242
1$
#5925760
0$
#5944278
1$
#5962796
0$
#5981314
1$
#5999832
0$
#6018350
1$
#6036868
0$
#6055386
1$
#6073904
0$
#6092422
1$
#6110940
0$
#6129458
1$
#6147976
0$
#6166494
1$
#6185012
0$
#6203530
1$
#6222048
0$
#6240566
1$
#6259084
0$
#6277602
1$
#6296120
0$
#6314638
1$
#6333156
0$
#6351674
1$
#6370192
0$
#6388710
1$
#6407228
0$
#6425746
1$
#6444264
0$
#6462782
1$
#6481300
0$
#6499818
1$
#6518336
0$
#6536854
1$
#6555372
0$
#6573890
1$
#6592408
0$
#6610926
1$
#6629444
0$
#6647962
1$
#6666480
0$
#6684998
1$
#6703516
0$
#6722034
1$
#6740552
0$
#6759070
1$
#6777588
0$
#6796106
1$
#6814624
0$
#6833142
1$
#6851660
0$
#6870178
1$
#6888696
0$
#6907214
1$
#6925732
0$
#6944250
1$
#6962768
0$
#6981286
1$
#6999804
0$
#7018322
1$
#7036840
0$
#7055358
1$
#7073876
0$
#7092394
1$
#7110912
0$
#7129430
1$
#7147948
0$
#7166466
1$
#7184984
0$
#7203502
1$
#7222020
0$
#7240538
1$
#7259056
0$
#7277574
1$
#7296092
0$
#7314610
1$
#7333128
0$
#7351646
1$
#7370164
0$
#7388682
1$
#7407200
0$
#7425718
1$
#7444236
0$
#7462754
1$
#7481272
0$
#7499790
1$
#7518308
0$
#7536826
1$
#7555344
0$
#7573862
1$
#7592380
0$
#7610898
1$
#7629416
0$
#7647934
1$
#7666452
0$
#7684970
1$
#7703488
0$
#7722006
1$
#7740524
0$
#7759042
1$
#7777560
0$
#7796078
1$
#7814596
0$
#7833114
1$
#7851632
0$
#7870150
1$
#7888668
0$
#7907186
1$
#7925704
0$
#7944222
1$
#7962740
0$
#7981258
1$
#7999776
0$
#8018294
1$
#8036812
0$
#8055330
1$
#8073848
0$
#8092366
1$
#8110884
0$
#8129402
1$
#8147920
0$
#8166438
1$
#8184956
0$
#8203474
1$
#8221992
0$
#8240510
1$
#8259028
0$
#8277546
1$
#8296064
0$
#8314582
1$
#8333100
0$
#8351618
1$
#8370136
0$
#8388654
1$
#8407172
0$
#8425690
1$
#8444208
0$
#8462726
1$
#8481244
0$
#8499762
1$
#8518280
0$
#8536798
1$
#8555316
0$
#8573834
1$
#8592352
0$
#8610870
1$
#8629388
0$
#8647906
1$
#8666424
0$
#8684942
1$
#8703460
0$
#8721978
1$
#8740496
0$
#8759014
1$
#8777532
0$
#8796050
1$
#8814568
0$
#8833086
1$
#8851604
0$
#8870122
1$
#8888640
0$
#8907158
1$
#8925676
0$
#8944194
1$
#8962712
0$
#8981230
1$
#8999748
0$
#9018266
1$
#9036784
0$
#9055302
1$
#9073820
0$
#9092338
1$
#9110856
0$
#9129374
1$
#9147892
0$
#9166410
1$
#9184928
0$
#9203446
1$
#9221964
0$
#9240482
1$
#9259000
0$
#9277518
1$
#9296036
0$
#9314554
1$
#9333072
0$
#9351590
1$
#9370108
0$
#9388626
1$
#9407144
0$
#9425662
1$
#9444180
0$
#9462698
1$
#9481216
0$
#9499734
1$
#9518252
0$
#9536770
1$
#9555288
0$
#9573806
1$
#9592324
0$
#9610842
1$
#9629360
0$
#9647878
1$
#9666396
0$
#9684914
1$
#9703432
0$
#9721950
1$
#9740468
0$
#9758986
1$
#9777504
0$
#9796022
1$
#9814540
0$
#9833058
1$
#9851576
0$
#9870094
1$
#9888612
0$
#9907130
1$
#9925648
0$
#9944166
1$
#9962684
0$
#9981202
1$
#9999720
0$
#10018238
1$
#10036756
0$
#10055274
1$
#10073792
0$
#10092310
1$
#10110828
0$
#10129346
1$
#10147864
0$
#10166382
1$
#10184900
0$
#10200000
1"
1.
#10203418
1(
1$
#10221936
0$
#10240454
1)
1$
#10258972
0$
#10277490
b11 ,
1$
#10296008
0$
#10314526
b11101 !
b11101 &
b10 '
b11 -
1$
