Verilog/17_FirFilter/firFilter/src/firFilter.sv
// Fixed-point finite impulse-response filter
// y[n] = c0*x[n] + c1*x[n-1] + c2*x[n-2] + c3*x[n-3]
// Moving-average filter, all coefficients = 0.25 -> 0.25 * 16 = 4 = 8'sh04
// => y[n] = 0.25*x[n] + 0.25*x[n-1] + 0.25*x[n-2] + 0.25*x[n-3]

module firFilter (
    input logic sys_clk,
    input logic sys_rst_n,

    input logic sampleValid,
    input logic signed [7:0] sampleIn,

    output logic outputValid,
    output logic signed [15:0] sampleOut
);

    // Fixed Q4.4 coefficients
    localparam logic signed [7:0] C0 = 8'sh04; // 0.25
    localparam logic signed [7:0] C1 = 8'sh04;
    localparam logic signed [7:0] C2 = 8'sh04;
    localparam logic signed [7:0] C3 = 8'sh04;

    // Delay line:
    // x0 = newest sample
    // x1 = previous sample
    // x2 = sample before that
    // x3 = oldest sample
    logic signed [7:0] x0;
    logic signed [7:0] x1;
    logic signed [7:0] x2;
    logic signed [7:0] x3;

    // Raw products
    // Q4.4 * Q4.4 = Q8.8
    // 8-bit * 8-bit = 16-bit product
    logic signed [15:0] p0Raw;
    logic signed [15:0] p1Raw;
    logic signed [15:0] p2Raw;
    logic signed [15:0] p3Raw;

    assign p0Raw = x0 * C0;
    assign p1Raw = x1 * C1;
    assign p2Raw = x2 * C2;
    assign p3Raw = x3 * C3;

    // Scaled products
    logic signed [15:0] p0;
    logic signed [15:0] p1;
    logic signed [15:0] p2;
    logic signed [15:0] p3;

    assign p0 = p0Raw >>> 4;
    assign p1 = p1Raw >>> 4;
    assign p2 = p2Raw >>> 4;
    assign p3 = p3Raw >>> 4;

    always_ff @(posedge sys_clk or negedge sys_rst_n) begin
        if (!sys_rst_n) begin
            x0 <= 8'sd0;
            x1 <= 8'sd0;
            x2 <= 8'sd0;
            x3 <= 8'sd0;

            outputValid <= 1'b0;
            sampleOut <= 16'sd0;
        end else begin
            outputValid <= 1'b0; // Default: no new output unless a new sample arrives
        
            if (sampleValid) begin
                // Shift delay line, new sample is x0, older samples move down the line
                x3 <= x2;
                x2 <= x1;
                x1 <= x0;
                x0 <= sampleIn;

                // Important:
                // Nonblocking assignments update after this clock edge, this sum uses the OLD x0/x1/x2/x3 values.
                // To include the new sampleIn immediately, we use sampleIn directly for the newest term instead of x0.
                sampleOut <= ((sampleIn * C0) >>> 4) + p0 + p1 + p2;

                outputValid <= 1'b1;
            end
        end
    end

endmodule

Verilog/17_FirFilter/sim/tb_firFilter.sv
`timescale 1ns/1ps

module tb_firFilter;

    logic sys_clk;
    logic sys_rst_n;

    logic sampleValid;
    logic signed [7:0] sampleIn;

    logic outputValid;
    logic signed [15:0] sampleOut;

    firFilter dut (
        .sys_clk(sys_clk),
        .sys_rst_n(sys_rst_n),
        .sampleValid(sampleValid),
        .sampleIn(sampleIn),
        .outputValid(outputValid),
        .sampleOut(sampleOut)
    );

    initial begin
        sys_clk = 1'b0;
        forever #18.518 sys_clk = ~sys_clk; // 27 MHz clock
    end

    task sendSample (input logic signed [7:0] inputSample);
        begin
            @(negedge sys_clk);
            sampleIn = inputSample;
            sampleValid = 1'b1;

            @(negedge sys_clk);
            sampleValid = 1'b0;
            sampleIn = 8'sd0;
        end
    endtask

    initial begin
        $dumpfile("sim/tb_firFilter.vcd");
        $dumpvars(0, tb_firFilter);

        sys_rst_n = 1'b0;
        sampleValid = 1'b0;
        sampleIn = 8'sd0;

        #200;
        sys_rst_n = 1'b1;

        // Feed constant 4.0.
        // 4.0 in Q4.4: 4.0 * 16 = 64 = 8'sh40
        // Coefficients are all 0.25.
        // Expected output ramp:
        // after 1st sample: 0.25 * 4.0 = 1.0 -> 16'sh0010
        // after 2nd sample: 0.50 * 4.0 = 2.0 -> 16'sh0020
        // after 3rd sample: 0.75 * 4.0 = 3.0 -> 16'sh0030
        // after 4th sample: 1.00 * 4.0 = 4.0 -> 16'sh0040
        sendSample(8'sh40);
        sendSample(8'sh40);
        sendSample(8'sh40);
        sendSample(8'sh40);
        sendSample(8'sh40);

        // Now feed zero. This shows the old samples leaving the delay line.
        // Expected output decay:
        // 3.0 -> 16'sh0030
        // 2.0 -> 16'sh0020
        // 1.0 -> 16'sh0010
        // 0.0 -> 16'sh0000
        sendSample(8'sh00);
        sendSample(8'sh00);
        sendSample(8'sh00);
        sendSample(8'sh00);

        // Signed test.
        // Feed -4.0: -4.0 * 16 = -64 = 8'shC0
        // Expected ramp:
        // -1.0 -> 16'shFFF0
        // -2.0 -> 16'shFFE0
        // -3.0 -> 16'shFFD0
        // -4.0 -> 16'shFFC0
        sendSample(8'shC0);
        sendSample(8'shC0);
        sendSample(8'shC0);
        sendSample(8'shC0);

        repeat (4) @(posedge sys_clk);

        $finish;
    end

endmodule

17_FirFilter/sim/tb_firFilter.vcd
$date
	Tue Jul  7 14:53:33 2026
$end
$version
	Icarus Verilog
$end
$timescale
	1ps
$end
$scope module tb_firFilter $end
$var wire 16 ! sampleOut [15:0] $end
$var wire 1 " outputValid $end
$var reg 8 # sampleIn [7:0] $end
$var reg 1 $ sampleValid $end
$var reg 1 % sys_clk $end
$var reg 1 & sys_rst_n $end
$scope module dut $end
$var wire 8 ' sampleIn [7:0] $end
$var wire 1 $ sampleValid $end
$var wire 1 % sys_clk $end
$var wire 1 & sys_rst_n $end
$var wire 16 ( p3Raw [15:0] $end
$var wire 16 ) p3 [15:0] $end
$var wire 16 * p2Raw [15:0] $end
$var wire 16 + p2 [15:0] $end
$var wire 16 , p1Raw [15:0] $end
$var wire 16 - p1 [15:0] $end
$var wire 16 . p0Raw [15:0] $end
$var wire 16 / p0 [15:0] $end
$var parameter 8 0 C0 $end
$var parameter 8 1 C1 $end
$var parameter 8 2 C2 $end
$var parameter 8 3 C3 $end
$var reg 1 " outputValid $end
$var reg 16 4 sampleOut [15:0] $end
$var reg 8 5 x0 [7:0] $end
$var reg 8 6 x1 [7:0] $end
$var reg 8 7 x2 [7:0] $end
$var reg 8 8 x3 [7:0] $end
$upscope $end
$scope task sendSample $end
$var reg 8 9 inputSample [7:0] $end
$upscope $end
$upscope $end
$enddefinitions $end
$comment Show the parameter values. $end
$dumpall
b100 3
b100 2
b100 1
b100 0
$end
#0
$dumpvars
bx 9
b0 8
b0 7
b0 6
b0 5
b0 4
b0 /
b0 .
b0 -
b0 ,
b0 +
b0 *
b0 )
b0 (
b0 '
0&
0%
0$
b0 #
0"
b0 !
$end
#18518
1%
#37036
0%
#55554
1%
#74072
0%
#92590
1%
#111108
0%
#129626
1%
#148144
0%
#166662
1%
#185180
0%
#200000
b1000000 9
1&
#203698
1%
#222216
1$
b1000000 #
b1000000 '
0%
#240734
b10000 /
1"
b10000 !
b10000 4
b100000000 .
b1000000 5
1%
#259252
b0 #
b0 '
0$
0%
#277770
0"
1%
#296288
1$
b1000000 #
b1000000 '
0%
#314806
b10000 -
1"
b100000 !
b100000 4
b100000000 ,
b1000000 6
1%
#333324
b0 #
b0 '
0$
0%
#351842
0"
1%
#370360
1$
b1000000 #
b1000000 '
0%
#388878
b10000 +
1"
b110000 !
b110000 4
b100000000 *
b1000000 7
1%
#407396
b0 #
b0 '
0$
0%
#425914
0"
1%
#444432
1$
b1000000 #
b1000000 '
0%
#462950
b10000 )
1"
b1000000 !
b1000000 4
b100000000 (
b1000000 8
1%
#481468
b0 #
b0 '
0$
0%
#499986
0"
1%
#518504
1$
b1000000 #
b1000000 '
0%
#537022
1"
1%
#555540
b0 9
b0 #
b0 '
0$
0%
#574058
0"
1%
#592576
1$
0%
#611094
b0 /
1"
b110000 !
b110000 4
b0 .
b0 5
1%
#629612
0$
0%
#648130
0"
1%
#666648
1$
0%
#685166
b0 -
1"
b100000 !
b100000 4
b0 ,
b0 6
1%
#703684
0$
0%
#722202
0"
1%
#740720
1$
0%
#759238
b0 +
1"
b10000 !
b10000 4
b0 *
b0 7
1%
#777756
0$
0%
#796274
0"
1%
#814792
1$
0%
#833310
b0 )
1"
b0 !
b0 4
b0 (
b0 8
1%
#851828
b11000000 9
0$
0%
#870346
0"
1%
#888864
1$
b11000000 #
b11000000 '
0%
#907382
b1111111111110000 /
1"
b1111111111110000 !
b1111111111110000 4
b1111111100000000 .
b11000000 5
1%
#925900
b0 #
b0 '
0$
0%
#944418
0"
1%
#962936
1$
b11000000 #
b11000000 '
0%
#981454
b1111111111110000 -
1"
b1111111111100000 !
b1111111111100000 4
b1111111100000000 ,
b11000000 6
1%
#999972
b0 #
b0 '
0$
0%
#1018490
0"
1%
#1037008
1$
b11000000 #
b11000000 '
0%
#1055526
b1111111111110000 +
1"
b1111111111010000 !
b1111111111010000 4
b1111111100000000 *
b11000000 7
1%
#1074044
b0 #
b0 '
0$
0%
#1092562
0"
1%
#1111080
1$
b11000000 #
b11000000 '
0%
#1129598
b1111111111110000 )
1"
b1111111111000000 !
b1111111111000000 4
b1111111100000000 (
b11000000 8
1%
#1148116
b0 #
b0 '
0$
0%
#1166634
0"
1%
