19_StreamInterface/streamInterface/src/streamRegister.sv
// One-word valid/ready stream register.
// Stores one DATA_WIDTH-wide word.

// A transfer happens only when valid && ready.
// If outputReady is 0, downstream is not ready.
// This block must hold outputValid and outputData stable.

module streamRegister #(
    parameter int DATA_WIDTH = 8
) (
    input logic sys_clk,
    input logic sys_rst_n,

    input logic inputValid,
    output logic inputReady,
    input logic [DATA_WIDTH-1:0] inputData,

    output logic outputValid,
    input logic outputReady,
    output logic [DATA_WIDTH-1:0] outputData
);

    logic full; // = 1 means outputDta contains a word, = 0 means register is empty
    assign inputReady = !full;

    always_ff @(posedge sys_clk or negedge sys_rst_n) begin
        if (!sys_rst_n) begin
            full <= 1'b0;
            outputValid <= 1'b0;
            outputData <= '0;
        end else begin
            if (outputValid && outputReady) begin
                full <= 1'b0;
                outputValid <= 1'b0;
            end

            if (inputValid && inputReady) begin
                outputData <= inputData;
                full <= 1'b1;
                outputValid <= 1'b1;
            end
        end
    end

endmodule

19_StreamInterface/sim/tb_streamRegister.sv
`timescale 1ns/1ps

module tb_streamRegister;

    logic sys_clk;
    logic sys_rst_n;

    logic inputValid;
    logic inputReady;
    logic [7:0] inputData;

    logic outputValid;
    logic outputReady;
    logic [7:0] outputData;

    streamRegister dut (
        .sys_clk(sys_clk),
        .sys_rst_n(sys_rst_n),
        .inputValid(inputValid),
        .inputReady(inputReady),
        .inputData(inputData),
        .outputValid(outputValid),
        .outputReady(outputReady),
        .outputData(outputData)
    );

    initial begin
        sys_clk = 1'b0;
        forever #18.518 sys_clk = ~sys_clk; // 27 MHz clock
    end

    // Offer one input word.
    // The task waits until inputReady is high because valid/ready
    // transfer only happens when both inputValid and inputReady are 1.
    task sendWord(input logic [7:0] dataByte);
        begin
            @(negedge sys_clk);
            inputData = dataByte;
            inputValid = 1'b1;

            while (!inputReady) begin
                @(negedge sys_clk);
            end

            @(negedge sys_clk);
            inputValid = 1'b0;
            inputData = 8'd0;
        end
    endtask

    initial begin
        $dumpfile("sim/tb_streamRegister.vcd");
        $dumpvars(0, tb_streamRegister);

        sys_rst_n = 1'b0;
        inputValid = 1'b0;
        inputData = 8'd0;
        outputReady = 1'b0;

        #200;
        sys_rst_n = 1'b1;

        // Normal transfer:
        // Downstream is ready before data arrives.
        // Expected:
        //   inputReady = 1
        //   data A1 is accepted
        //   outputValid becomes 1
        //   outputData = A1
        //   outputReady consumes it
        outputReady = 1'b1;
        sendWord(8'hA1);

        repeat (2) @(posedge sys_clk);

        // Backpressure:
        // Downstream is not ready.
        // Expected:
        //   data B2 is accepted into the register
        //   outputValid stays 1
        //   outputData stays B2
        //   inputReady goes 0 because the register is full
        outputReady = 1'b0;
        sendWord(8'hB2);

        repeat (4) @(posedge sys_clk);

        // Release backpressure:
        // Downstream becomes ready again.
        // Expected:
        //   outputValid && outputReady happens
        //   stored B2 transfers out
        //   register becomes empty
        //   inputReady returns to 1
        outputReady = 1'b1;

        repeat (3) @(posedge sys_clk);

        // Another normal transfer after release.
        sendWord(8'hC3);

        repeat (4) @(posedge sys_clk);

        $finish;
    end

endmodule

Verilog/19_StreamInterface/sim/tb_streamRegister.vcd
$date
	Tue Jul  7 17:12:55 2026
$end
$version
	Icarus Verilog
$end
$timescale
	1ps
$end
$scope module tb_streamRegister $end
$var wire 1 ! outputValid $end
$var wire 8 " outputData [7:0] $end
$var wire 1 # inputReady $end
$var reg 8 $ inputData [7:0] $end
$var reg 1 % inputValid $end
$var reg 1 & outputReady $end
$var reg 1 ' sys_clk $end
$var reg 1 ( sys_rst_n $end
$scope module dut $end
$var wire 8 ) inputData [7:0] $end
$var wire 1 % inputValid $end
$var wire 1 & outputReady $end
$var wire 1 ' sys_clk $end
$var wire 1 ( sys_rst_n $end
$var wire 1 # inputReady $end
$var parameter 32 * DATA_WIDTH $end
$var reg 1 + full $end
$var reg 8 , outputData [7:0] $end
$var reg 1 ! outputValid $end
$upscope $end
$scope task sendWord $end
$var reg 8 - dataByte [7:0] $end
$upscope $end
$upscope $end
$enddefinitions $end
$comment Show the parameter values. $end
$dumpall
b1000 *
$end
#0
$dumpvars
bx -
b0 ,
0+
b0 )
0(
0'
0&
0%
b0 $
1#
b0 "
0!
$end
#18518
1'
#37036
0'
#55554
1'
#74072
0'
#92590
1'
#111108
0'
#129626
1'
#148144
0'
#166662
1'
#185180
0'
#200000
b10100001 -
1&
1(
#203698
1'
#222216
1%
b10100001 $
b10100001 )
0'
#240734
1!
0#
1+
b10100001 "
b10100001 ,
1'
#259252
b0 $
b0 )
0%
0'
#277770
0!
1#
0+
1'
#296288
0'
#314806
b10110010 -
0&
1'
#333324
1%
b10110010 $
b10110010 )
0'
#351842
1!
0#
1+
b10110010 "
b10110010 ,
1'
#370360
b0 $
b0 )
0%
0'
#388878
1'
#407396
0'
#425914
1'
#444432
0'
#462950
1'
#481468
0'
#499986
0!
1#
0+
1&
1'
#518504
0'
#537022
1'
#555540
0'
#574058
1'
#592576
0'
#611094
b11000011 -
1'
#629612
1%
b11000011 $
b11000011 )
0'
#648130
1!
0#
1+
b11000011 "
b11000011 ,
1'
#666648
b0 $
b0 )
0%
0'
#685166
0!
1#
0+
1'
