Verilog/22_AxiLiteRegisterBlock/axiLiteRegisterBlock/src/axiLiteRegisterBlock.sv
// Simplified register-bus model to teach core ideas
// CPU controls registers with sofware, hardware uses registers for operation and writes result back to registers, CPU receives result from registers

module axiLiteRegisterBlock (
    input logic sys_clk,
    input logic sys_rst_n,

    input logic writeEnable,
    input logic [7:0] writeAddress,
    input logic [31:0] writeData,

    input logic readEnable,
    input logic [7:0] readAddress,
    output logic [31:0] readData,

    output logic done,
    output logic busy
);
    
    // The +4 spacing is because each register is 32 bits = 4 bytes
    localparam logic [7:0] ADDR_CONTROL = 8'h00;
    localparam logic [7:0] ADDR_INPUT_A = 8'h04;
    localparam logic [7:0] ADDR_INPUT_B = 8'h08;
    localparam logic [7:0] ADDR_RESULT  = 8'h0C;
    localparam logic [7:0] ADDR_STATUS  = 8'h10;

    logic [31:0] controlReg;
    logic [31:0] inputAReg;
    logic [31:0] inputBReg;
    logic [31:0] resultReg;
    logic [31:0] statusReg;

    logic startPulse;

    // startPulse is true for one clock when software writes 1 to control bit 0
    assign startPulse = writeEnable && (writeAddress == ADDR_CONTROL) && writeData[0];

    assign done = statusReg[0];
    assign busy = statusReg[1];

        always_ff @(posedge sys_clk or negedge sys_rst_n) begin
        if (!sys_rst_n) begin
            controlReg <= 32'd0;
            inputAReg <= 32'd0;
            inputBReg <= 32'd0;
            resultReg <= 32'd0;
            statusReg <= 32'd0;
        end else begin
            // Default: done is a sticky status bit until a new operation starts
            // busy stays controlled by the operation state below.

            if (writeEnable) begin
                case (writeAddress)
                    ADDR_CONTROL: begin
                        controlReg <= writeData;
                    end

                    ADDR_INPUT_A: begin
                        inputAReg <= writeData;
                    end

                    ADDR_INPUT_B: begin
                        inputBReg <= writeData;
                    end

                    default: begin
                        // Writes to read-only or unmapped addresses are ignored
                    end
                endcase
            end

            if (startPulse) begin
                statusReg[0] <= 1'b0; // done = 0
                statusReg[1] <= 1'b1; // busy = 1

                // Simple one-cycle "hardware accelerator":
                resultReg <= inputAReg + inputBReg;

                // Since this operation is combinational/simple, finish immediately
                statusReg[0] <= 1'b1; // done = 1
                statusReg[1] <= 1'b0; // busy = 0
            end
        end
    end

    // Combinational read mux
    // The bus master chooses an address. This block returns the register value at that address
    always_comb begin
        if (readEnable) begin
            case (readAddress)
                ADDR_CONTROL: begin
                    readData = controlReg;
                end

                ADDR_INPUT_A: begin
                    readData = inputAReg;
                end

                ADDR_INPUT_B: begin
                    readData = inputBReg;
                end

                ADDR_RESULT: begin
                    readData = resultReg;
                end

                ADDR_STATUS: begin
                    readData = statusReg;
                end

                default: begin
                    readData = 32'd0;
                end
            endcase
        end else begin
            readData = 32'd0;
        end
    end

endmodule

Verilog/22_AxiLiteRegisterBlock/sim/tb_axiLiteRegisterBlock.sv
`timescale 1ns/1ps

module tb_axiLiteRegisterBlock;

    logic sys_clk;
    logic sys_rst_n;

    logic writeEnable;
    logic [7:0] writeAddress;
    logic [31:0] writeData;

    logic readEnable;
    logic [7:0] readAddress;
    logic [31:0] readData;

    logic done;
    logic busy;

    localparam logic [7:0] ADDR_CONTROL = 8'h00;
    localparam logic [7:0] ADDR_INPUT_A = 8'h04;
    localparam logic [7:0] ADDR_INPUT_B = 8'h08;
    localparam logic [7:0] ADDR_RESULT  = 8'h0C;
    localparam logic [7:0] ADDR_STATUS  = 8'h10;

    axiLiteRegisterBlock dut (
        .sys_clk(sys_clk),
        .sys_rst_n(sys_rst_n),

        .writeEnable(writeEnable),
        .writeAddress(writeAddress),
        .writeData(writeData),

        .readEnable(readEnable),
        .readAddress(readAddress),
        .readData(readData),

        .done(done),
        .busy(busy)
    );

    initial begin
        sys_clk = 1'b0;
        forever #18.518 sys_clk = ~sys_clk; // 27 MHz clock
    end

    // Simulated bus write
    task busWrite(input logic [7:0] address, input logic [31:0] data);
        begin
            @(negedge sys_clk);
            writeAddress = address;
            writeData = data;
            writeEnable = 1'b1;

            @(negedge sys_clk);
            writeEnable = 1'b0;
            writeAddress = 8'd0;
            writeData = 32'd0;
        end
    endtask

    // Simulated bus read
    task busRead(input logic [7:0] address);
        begin
            @(negedge sys_clk);
            readAddress = address;
            readEnable = 1'b1;

            @(negedge sys_clk);
            readEnable = 1'b0;
            readAddress = 8'd0;
        end
    endtask

    initial begin
        $dumpfile("sim/tb_axiLiteRegisterBlock.vcd");
        $dumpvars(0, tb_axiLiteRegisterBlock);

        sys_rst_n = 1'b0;

        writeEnable = 1'b0;
        writeAddress = 8'd0;
        writeData = 32'd0;

        readEnable = 1'b0;
        readAddress = 8'd0;

        #200;
        sys_rst_n = 1'b1;

        // Software writes operands.
        busWrite(ADDR_INPUT_A, 32'd15);
        busWrite(ADDR_INPUT_B, 32'd27);

        // Software starts hardware operation
        // control bit 0 = start
        busWrite(ADDR_CONTROL, 32'h0000_0001);

        // Software reads result
        // Expected: result = 15 + 27 = 42 = 0x0000002A
        busRead(ADDR_RESULT);

        // Software reads status
        // Expected: status bit 0 done = 1, status bit 1 busy = 0, status = 0x00000001
        busRead(ADDR_STATUS);

        // Second operation
        busWrite(ADDR_INPUT_A, 32'd100);
        busWrite(ADDR_INPUT_B, 32'd23);
        busWrite(ADDR_CONTROL, 32'h0000_0001);

        // Expected: result = 123 = 0x0000007B
        busRead(ADDR_RESULT);
        busRead(ADDR_STATUS);

        repeat (4) @(posedge sys_clk);

        $finish;
    end

endmodule

Verilog/22_AxiLiteRegisterBlock/sim/tb_axiLiteRegisterBlock.vcd
$date
	Fri Jul 10 15:04:33 2026
$end
$version
	Icarus Verilog
$end
$timescale
	1ps
$end
$scope module tb_axiLiteRegisterBlock $end
$var wire 32 ! readData [31:0] $end
$var wire 1 " done $end
$var wire 1 # busy $end
$var parameter 8 $ ADDR_CONTROL $end
$var parameter 8 % ADDR_INPUT_A $end
$var parameter 8 & ADDR_INPUT_B $end
$var parameter 8 ' ADDR_RESULT $end
$var parameter 8 ( ADDR_STATUS $end
$var reg 8 ) readAddress [7:0] $end
$var reg 1 * readEnable $end
$var reg 1 + sys_clk $end
$var reg 1 , sys_rst_n $end
$var reg 8 - writeAddress [7:0] $end
$var reg 32 . writeData [31:0] $end
$var reg 1 / writeEnable $end
$scope module dut $end
$var wire 8 0 readAddress [7:0] $end
$var wire 1 * readEnable $end
$var wire 1 1 startPulse $end
$var wire 1 + sys_clk $end
$var wire 1 , sys_rst_n $end
$var wire 8 2 writeAddress [7:0] $end
$var wire 32 3 writeData [31:0] $end
$var wire 1 / writeEnable $end
$var wire 1 " done $end
$var wire 1 # busy $end
$var parameter 8 4 ADDR_CONTROL $end
$var parameter 8 5 ADDR_INPUT_A $end
$var parameter 8 6 ADDR_INPUT_B $end
$var parameter 8 7 ADDR_RESULT $end
$var parameter 8 8 ADDR_STATUS $end
$var reg 32 9 controlReg [31:0] $end
$var reg 32 : inputAReg [31:0] $end
$var reg 32 ; inputBReg [31:0] $end
$var reg 32 < readData [31:0] $end
$var reg 32 = resultReg [31:0] $end
$var reg 32 > statusReg [31:0] $end
$upscope $end
$scope task busRead $end
$var reg 8 ? address [7:0] $end
$upscope $end
$scope task busWrite $end
$var reg 8 @ address [7:0] $end
$var reg 32 A data [31:0] $end
$upscope $end
$upscope $end
$enddefinitions $end
$comment Show the parameter values. $end
$dumpall
b10000 8
b1100 7
b1000 6
b100 5
b0 4
b10000 (
b1100 '
b1000 &
b100 %
b0 $
$end
#0
$dumpvars
bx A
bx @
bx ?
b0 >
b0 =
b0 <
b0 ;
b0 :
b0 9
b0 3
b0 2
01
b0 0
0/
b0 .
b0 -
0,
0+
0*
b0 )
0#
0"
b0 !
$end
#18518
1+
#37036
0+
#55554
1+
#74072
0+
#92590
1+
#111108
0+
#129626
1+
#148144
0+
#166662
1+
#185180
0+
#200000
b1111 A
b100 @
1,
#203698
1+
#222216
1/
b1111 .
b1111 3
b100 -
b100 2
0+
#240734
b1111 :
1+
#259252
b11011 A
b1000 @
b0 .
b0 3
b0 -
b0 2
0/
0+
#277770
1+
#296288
1/
b11011 .
b11011 3
b1000 -
b1000 2
0+
#314806
b11011 ;
1+
#333324
b1 A
b0 @
b0 .
b0 3
b0 -
b0 2
0/
0+
#351842
1+
#370360
11
1/
b1 .
b1 3
0+
#388878
1"
b101010 =
b1 >
b1 9
1+
#407396
01
b1100 ?
b0 .
b0 3
0/
0+
#425914
1+
#444432
b101010 !
b101010 <
1*
b1100 )
b1100 0
0+
#462950
1+
#481468
b0 !
b0 <
b10000 ?
b0 )
b0 0
0*
0+
#499986
1+
#518504
b1 !
b1 <
1*
b10000 )
b10000 0
0+
#537022
1+
#555540
b0 !
b0 <
b1100100 A
b100 @
b0 )
b0 0
0*
0+
#574058
1+
#592576
1/
b1100100 .
b1100100 3
b100 -
b100 2
0+
#611094
b1100100 :
1+
#629612
b10111 A
b1000 @
b0 .
b0 3
b0 -
b0 2
0/
0+
#648130
1+
#666648
1/
b10111 .
b10111 3
b1000 -
b1000 2
0+
#685166
b10111 ;
1+
#703684
b1 A
b0 @
b0 .
b0 3
b0 -
b0 2
0/
0+
#722202
1+
#740720
11
1/
b1 .
b1 3
0+
#759238
b1111011 =
b1 >
1+
#777756
01
b1100 ?
b0 .
b0 3
0/
0+
#796274
1+
#814792
b1111011 !
b1111011 <
1*
b1100 )
b1100 0
0+
#833310
1+
#851828
b0 !
b0 <
b10000 ?
b0 )
b0 0
0*
0+
#870346
1+
#888864
b1 !
b1 <
1*
b10000 )
b10000 0
0+
#907382
1+
#925900
b0 !
b0 <
b0 )
b0 0
0*
0+
