25_FormalFifoChecks/checkedSyncFifo/src/checkedSyncFifo.sv
// Adds verification checks to a FIFO
// "Did the design ever violate a rule?"

module checkedSyncFifo #(
    parameter int DATA_WIDTH = 8,
    parameter int DEPTH = 16,
    parameter int ADDR_WIDTH = 4
) (
    input logic sys_clk,
    input logic sys_rst_n,

    input logic writeEnable,
    input logic [DATA_WIDTH-1:0] writeData,
    output logic full,

    input logic readEnable,
    output logic [DATA_WIDTH-1:0] readData,
    output logic empty,

    output logic [ADDR_WIDTH:0] count
);

    logic [DATA_WIDTH-1:0] memory [0:DEPTH-1];

    logic [ADDR_WIDTH-1:0] writePointer;
    logic [ADDR_WIDTH-1:0] readPointer;

    logic writeValid;
    logic readValid;

    assign full = (count == DEPTH);
    assign empty = (count == 0);

    assign writeValid = writeEnable && !full;
    assign readValid = readEnable && !empty;

    always_ff @(posedge sys_clk or negedge sys_rst_n) begin
        if (!sys_rst_n) begin
            writePointer <= '0;
            readPointer <= '0;
            readData <= '0;
            count <= '0;
        end else begin
            if (writeValid) begin
                memory[writePointer] <= writeData;
                writePointer <= writePointer + 1'b1;
            end

            if (readValid) begin
                readData <= memory[readPointer];
                readPointer <= readPointer + 1'b1;
            end

            case ({writeValid, readValid})
                2'b10: begin
                    count <= count + 1'b1;
                end

                2'b01: begin
                    count <= count - 1'b1;
                end

                default: begin
                    count <= count;
                end
            endcase
        end
    end

    // Assertions below are checked during simulation
    // If a condition becomes false, the simulator prints an error
    // `ifndef SYNTHESIS prevents these checks from being synthesized into FPGA hardware by synthesis tools.

    `ifndef SYNTHESIS

    // Previous-cycle copies
    // These help check that illegal writes/reads did not incorrectly change count
    logic [ADDR_WIDTH:0] previousCount;
    logic previousFull;
    logic previousEmpty;
    logic previousWriteEnable;
    logic previousReadEnable;

    always_ff @(posedge sys_clk or negedge sys_rst_n) begin
        if (!sys_rst_n) begin
            previousCount <= '0;
            previousFull <= 1'b0;
            previousEmpty <= 1'b1;
            previousWriteEnable <= 1'b0;
            previousReadEnable <= 1'b0;
        end else begin
            previousCount <= count;
            previousFull <= full;
            previousEmpty <= empty;
            previousWriteEnable <= writeEnable;
            previousReadEnable <= readEnable;
        end
    end

    always_ff @(posedge sys_clk) begin
        if (sys_rst_n) begin
            // Count must never exceed FIFO depth
            assert (count <= DEPTH)
                else $error("ASSERT FAILED: count exceeded DEPTH. count=%0d DEPTH=%0d", count, DEPTH);

            // Flag consistency
            assert (full == (count == DEPTH))
                else $error("ASSERT FAILED: full flag inconsistent with count.");

            assert (empty == (count == 0))
                else $error("ASSERT FAILED: empty flag inconsistent with count.");

            // full and empty should not both be true for a nonzero-depth FIFO
            assert (!(full && empty))
                else $error("ASSERT FAILED: full and empty both high.");

            // If previous cycle attempted write while full and no read happened, count must not increase
            if (previousWriteEnable && previousFull && !previousReadEnable) begin
                assert (count == previousCount)
                    else $error("ASSERT FAILED: write while full changed count.");
            end

            // If previous cycle attempted read while empty and no write happened, count must not decrease
            if (previousReadEnable && previousEmpty && !previousWriteEnable) begin
                assert (count == previousCount)
                    else $error("ASSERT FAILED: read while empty changed count.");
            end
        end
    end

    `endif

endmodule

Verilog/25_FormalFifoChecks/sim/tb_checkedSyncFifo.sv
`timescale 1ns/1ps

module tb_checkedSyncFifo;

    logic sys_clk;
    logic sys_rst_n;

    logic writeEnable;
    logic [7:0] writeData;
    logic full;

    logic readEnable;
    logic [7:0] readData;
    logic empty;

    logic [4:0] count;

    checkedSyncFifo dut (
        .sys_clk(sys_clk),
        .sys_rst_n(sys_rst_n),

        .writeEnable(writeEnable),
        .writeData(writeData),
        .full(full),

        .readEnable(readEnable),
        .readData(readData),
        .empty(empty),

        .count(count)
    );

    initial begin
        sys_clk = 1'b0;
        forever #18.518 sys_clk = ~sys_clk; // 27 MHz clock
    end

    task writeByte(input logic [7:0] dataByte);
        begin
            @(negedge sys_clk);
            writeData = dataByte;
            writeEnable = 1'b1;

            @(negedge sys_clk);
            writeEnable = 1'b0;
            writeData = 8'd0;
        end
    endtask

    task readByte;
        begin
            @(negedge sys_clk);
            readEnable = 1'b1;

            @(negedge sys_clk);
            readEnable = 1'b0;
        end
    endtask

    initial begin
        $dumpfile("sim/tb_checkedSyncFifo.vcd");
        $dumpvars(0, tb_checkedSyncFifo);

        sys_rst_n = 1'b0;
        writeEnable = 1'b0;
        writeData = 8'd0;
        readEnable = 1'b0;

        #200;
        sys_rst_n = 1'b1;

        // Reset condition should produce: count = 0, empty = 1, full  = 0
        repeat (2) @(posedge sys_clk);

        // Normal writes
        // Expected: count increases to 3
        writeByte(8'h11);
        writeByte(8'h22);
        writeByte(8'h33);

        // Normal reads
        // Expected: count decreases back to 0
        readByte();
        readByte();
        readByte();

        // Try to read while empty
        // Expected: no underflow, count remains 0
        readByte();

        // Fill FIFO completely
        // Expected: count reaches 16, full becomes 1
        writeByte(8'hA0);
        writeByte(8'hA1);
        writeByte(8'hA2);
        writeByte(8'hA3);
        writeByte(8'hA4);
        writeByte(8'hA5);
        writeByte(8'hA6);
        writeByte(8'hA7);
        writeByte(8'hA8);
        writeByte(8'hA9);
        writeByte(8'hAA);
        writeByte(8'hAB);
        writeByte(8'hAC);
        writeByte(8'hAD);
        writeByte(8'hAE);
        writeByte(8'hAF);

        // Try to write while full
        // Expected: no overflow, count remains 16
        writeByte(8'hFF);

        // Drain part of FIFO
        readByte();
        readByte();
        readByte();
        readByte();

        // Simultaneous read and write
        // Expected: count unchanged
        @(negedge sys_clk);
        writeData = 8'h55;
        writeEnable = 1'b1;
        readEnable = 1'b1;

        @(negedge sys_clk);
        writeEnable = 1'b0;
        readEnable = 1'b0;
        writeData = 8'd0;

        repeat (8) @(posedge sys_clk);

        $display("checkedSyncFifo simulation completed.");

        $finish;
    end

endmodule

25_FormalFifoChecks/sim/tb_checkedSyncFifo.vcd
$date
	Fri Jul 10 17:28:54 2026
$end
$version
	Icarus Verilog
$end
$timescale
	1ps
$end
$scope module tb_checkedSyncFifo $end
$var wire 8 ! readData [7:0] $end
$var wire 1 " full $end
$var wire 1 # empty $end
$var wire 5 $ count [4:0] $end
$var reg 1 % readEnable $end
$var reg 1 & sys_clk $end
$var reg 1 ' sys_rst_n $end
$var reg 8 ( writeData [7:0] $end
$var reg 1 ) writeEnable $end
$scope module dut $end
$var wire 1 % readEnable $end
$var wire 1 * readValid $end
$var wire 1 & sys_clk $end
$var wire 1 ' sys_rst_n $end
$var wire 8 + writeData [7:0] $end
$var wire 1 ) writeEnable $end
$var wire 1 , writeValid $end
$var wire 1 " full $end
$var wire 1 # empty $end
$var parameter 32 - ADDR_WIDTH $end
$var parameter 32 . DATA_WIDTH $end
$var parameter 32 / DEPTH $end
$var reg 5 0 count [4:0] $end
$var reg 5 1 previousCount [4:0] $end
$var reg 1 2 previousEmpty $end
$var reg 1 3 previousFull $end
$var reg 1 4 previousReadEnable $end
$var reg 1 5 previousWriteEnable $end
$var reg 8 6 readData [7:0] $end
$var reg 4 7 readPointer [3:0] $end
$var reg 4 8 writePointer [3:0] $end
$upscope $end
$scope task readByte $end
$upscope $end
$scope task writeByte $end
$var reg 8 9 dataByte [7:0] $end
$upscope $end
$upscope $end
$enddefinitions $end
$comment Show the parameter values. $end
$dumpall
b10000 /
b1000 .
b100 -
$end
#0
$dumpvars
bx 9
b0 8
b0 7
b0 6
05
04
03
12
b0 1
b0 0
0,
b0 +
0*
0)
b0 (
0'
0&
0%
b0 $
1#
0"
b0 !
$end
#18518
1&
#37036
0&
#55554
1&
#74072
0&
#92590
1&
#111108
0&
#129626
1&
#148144
0&
#166662
1&
#185180
0&
#200000
1'
#203698
1&
#222216
0&
#240734
b10001 9
1&
#259252
1,
1)
b10001 (
b10001 +
0&
#277770
0#
b1 $
b1 0
b1 8
15
1&
#296288
0,
b100010 9
b0 (
b0 +
0)
0&
#314806
05
02
b1 1
1&
#333324
1,
1)
b100010 (
b100010 +
0&
#351842
b10 $
b10 0
b10 8
15
1&
#370360
0,
b110011 9
b0 (
b0 +
0)
0&
#388878
05
b10 1
1&
#407396
1,
1)
b110011 (
b110011 +
0&
#425914
b11 $
b11 0
b11 8
15
1&
#444432
0,
b0 (
b0 +
0)
0&
#462950
05
b11 1
1&
#481468
1*
1%
0&
#499986
b10 $
b10 0
b1 7
b10001 !
b10001 6
14
1&
#518504
0*
0%
0&
#537022
04
b10 1
1&
#555540
1*
1%
0&
#574058
b1 $
b1 0
b10 7
b100010 !
b100010 6
14
1&
#592576
0*
0%
0&
#611094
04
b1 1
1&
#629612
1*
1%
0&
#648130
0*
1#
b0 $
b0 0
b11 7
b110011 !
b110011 6
14
1&
#666648
0%
0&
#685166
04
12
b0 1
1&
#703684
1%
0&
#722202
14
1&
#740720
b10100000 9
0%
0&
#759238
04
1&
#777756
1,
1)
b10100000 (
b10100000 +
0&
#796274
0#
b1 $
b1 0
b100 8
15
1&
#814792
0,
b10100001 9
b0 (
b0 +
0)
0&
#833310
05
02
b1 1
1&
#851828
1,
1)
b10100001 (
b10100001 +
0&
#870346
b10 $
b10 0
b101 8
15
1&
#888864
0,
b10100010 9
b0 (
b0 +
0)
0&
#907382
05
b10 1
1&
#925900
1,
1)
b10100010 (
b10100010 +
0&
#944418
b11 $
b11 0
b110 8
15
1&
#962936
0,
b10100011 9
b0 (
b0 +
0)
0&
#981454
05
b11 1
1&
#999972
1,
1)
b10100011 (
b10100011 +
0&
#1018490
b100 $
b100 0
b111 8
15
1&
#1037008
0,
b10100100 9
b0 (
b0 +
0)
0&
#1055526
05
b100 1
1&
#1074044
1,
1)
b10100100 (
b10100100 +
0&
#1092562
b101 $
b101 0
b1000 8
15
1&
#1111080
0,
b10100101 9
b0 (
b0 +
0)
0&
#1129598
05
b101 1
1&
#1148116
1,
1)
b10100101 (
b10100101 +
0&
#1166634
b110 $
b110 0
b1001 8
15
1&
#1185152
0,
b10100110 9
b0 (
b0 +
0)
0&
#1203670
05
b110 1
1&
#1222188
1,
1)
b10100110 (
b10100110 +
0&
#1240706
b111 $
b111 0
b1010 8
15
1&
#1259224
0,
b10100111 9
b0 (
b0 +
0)
0&
#1277742
05
b111 1
1&
#1296260
1,
1)
b10100111 (
b10100111 +
0&
#1314778
b1000 $
b1000 0
b1011 8
15
1&
#1333296
0,
b10101000 9
b0 (
b0 +
0)
0&
#1351814
05
b1000 1
1&
#1370332
1,
1)
b10101000 (
b10101000 +
0&
#1388850
b1001 $
b1001 0
b1100 8
15
1&
#1407368
0,
b10101001 9
b0 (
b0 +
0)
0&
#1425886
05
b1001 1
1&
#1444404
1,
1)
b10101001 (
b10101001 +
0&
#1462922
b1010 $
b1010 0
b1101 8
15
1&
#1481440
0,
b10101010 9
b0 (
b0 +
0)
0&
#1499958
05
b1010 1
1&
#1518476
1,
1)
b10101010 (
b10101010 +
0&
#1536994
b1011 $
b1011 0
b1110 8
15
1&
#1555512
0,
b10101011 9
b0 (
b0 +
0)
0&
#1574030
05
b1011 1
1&
#1592548
1,
1)
b10101011 (
b10101011 +
0&
#1611066
b1100 $
b1100 0
b1111 8
15
1&
#1629584
0,
b10101100 9
b0 (
b0 +
0)
0&
#1648102
05
b1100 1
1&
#1666620
1,
1)
b10101100 (
b10101100 +
0&
#1685138
b1101 $
b1101 0
b0 8
15
1&
#1703656
0,
b10101101 9
b0 (
b0 +
0)
0&
#1722174
05
b1101 1
1&
#1740692
1,
1)
b10101101 (
b10101101 +
0&
#1759210
b1110 $
b1110 0
b1 8
15
1&
#1777728
0,
b10101110 9
b0 (
b0 +
0)
0&
#1796246
05
b1110 1
1&
#1814764
1,
1)
b10101110 (
b10101110 +
0&
#1833282
b1111 $
b1111 0
b10 8
15
1&
#1851800
0,
b10101111 9
b0 (
b0 +
0)
0&
#1870318
05
b1111 1
1&
#1888836
1,
1)
b10101111 (
b10101111 +
0&
#1907354
0,
1"
b10000 $
b10000 0
b11 8
15
1&
#1925872
b11111111 9
b0 (
b0 +
0)
0&
#1944390
05
13
b10000 1
1&
#1962908
1)
b11111111 (
b11111111 +
0&
#1981426
15
1&
#1999944
b0 (
b0 +
0)
0&
#2018462
05
1&
#2036980
1*
1%
0&
#2055498
0"
b1111 $
b1111 0
b100 7
b10100000 !
b10100000 6
14
1&
#2074016
0*
0%
0&
#2092534
04
03
b1111 1
1&
#2111052
1*
1%
0&
#2129570
b1110 $
b1110 0
b101 7
b10100001 !
b10100001 6
14
1&
#2148088
0*
0%
0&
#2166606
04
b1110 1
1&
#2185124
1*
1%
0&
#2203642
b1101 $
b1101 0
b110 7
b10100010 !
b10100010 6
14
1&
#2222160
0*
0%
0&
#2240678
04
b1101 1
1&
#2259196
1*
1%
0&
#2277714
b1100 $
b1100 0
b111 7
b10100011 !
b10100011 6
14
1&
#2296232
0*
0%
0&
#2314750
04
b1100 1
1&
#2333268
1*
1,
1%
1)
b1010101 (
b1010101 +
0&
#2351786
b1000 7
b10100100 !
b10100100 6
b100 8
14
15
1&
#2370304
0*
0,
b0 (
b0 +
0%
0)
0&
#2388822
04
05
1&
