Verilog/29_SimpleMotorControl/simpleMotorControl/src/motorModel.sv
// Simple simulated motor/plant model

module motorModel (
    input logic sys_clk,
    input logic sys_rst_n,

    input logic sampleEnable,
    input logic signed [15:0] command,

    output logic signed [15:0] measuredPosition
);

    logic signed [31:0] position;
    logic signed [31:0] velocity;

    logic signed [31:0] commandExtended;
    logic signed [31:0] damping;
    logic signed [31:0] acceleration;
    logic signed [31:0] nextVelocity;
    logic signed [31:0] nextPosition;

    assign commandExtended = {{16{command[15]}}, command};

    // Damping
    // If velocity is positive, damping is positive and reduces acceleration
    // If velocity is negative, damping is negative and also opposes motion
    assign damping = velocity >>> 3;
    assign acceleration = commandExtended - damping;

    // Divide acceleration by 8 to make the model slower and more stable
    assign nextVelocity = velocity + (acceleration >>> 3);

    // Divide velocity by 16 before adding to position
    // This makes position change gradually sample by sample
    assign nextPosition = position + (nextVelocity >>> 4);

    function automatic logic signed [15:0] saturate16(input logic signed [31:0] value);
        begin
            if (value > 32'sd32767) begin
                saturate16 = 16'sh7FFF;
            end else if (value < -32'sd32768) begin
                saturate16 = 16'sh8000;
            end else begin
                saturate16 = 16'(value);
            end
        end
    endfunction

    always_ff @(posedge sys_clk or negedge sys_rst_n) begin
        if (!sys_rst_n) begin
            position <= 32'sd0;
            velocity <= 32'sd0;
            measuredPosition <= 16'sd0;
        end else begin
            if (sampleEnable) begin
                velocity <= nextVelocity;
                position <= nextPosition;
                measuredPosition <= saturate16(nextPosition);
            end
        end
    end

endmodule

Verilog/29_SimpleMotorControl/simpleMotorControl/src/pidMotorControl.sv
module pidMotorControl (
    input logic sys_clk,
    input logic sys_rst_n,

    input logic sampleEnable,

    input logic signed [15:0] setpoint,
    input logic signed [15:0] measuredValue,

    input logic signed [15:0] kp,
    input logic signed [15:0] ki,
    input logic signed [15:0] kd,

    output logic signed [15:0] controlOutput,
    output logic outputValid
);

    logic signed [15:0] currentError;
    logic signed [15:0] previousError;
    logic signed [15:0] errorDelta;

    logic signed [31:0] integralAccumulator;

    logic signed [31:0] proportionalProduct;
    logic signed [47:0] integralProduct;
    logic signed [31:0] derivativeProduct;

    logic signed [31:0] proportionalTerm;
    logic signed [31:0] integralTerm;
    logic signed [31:0] derivativeTerm;

    logic signed [31:0] pidSum;

    assign currentError = setpoint - measuredValue;
    assign errorDelta = currentError - previousError;

    // Q8.8 * Q8.8 = Q16.16
    assign proportionalProduct = currentError * kp;

    // integralAccumulator is 32-bit Q24.8
    // Multiplying by Q8.8 gives Q32.16
    assign integralProduct = integralAccumulator * ki;

    // Q8.8 * Q8.8 = Q16.16
    assign derivativeProduct = errorDelta * kd;

    // Shift right by 8 to convert Q16.16 back to Q24.8 / Q8.8 scale
    assign proportionalTerm = proportionalProduct >>> 8;
    assign integralTerm = integralProduct >>> 8;
    assign derivativeTerm = derivativeProduct >>> 8;

    assign pidSum = proportionalTerm + integralTerm + derivativeTerm;

    function automatic logic signed [15:0] saturate16(input logic signed [31:0] value);
        begin
            if (value > 32'sd32767) begin
                saturate16 = 16'sh7FFF;
            end else if (value < -32'sd32768) begin
                saturate16 = 16'sh8000;
            end else begin
                saturate16 = 16'(value);
            end
        end
    endfunction

    always_ff @(posedge sys_clk or negedge sys_rst_n) begin
        if (!sys_rst_n) begin
            previousError <= 16'sd0;
            integralAccumulator <= 32'sd0;
            controlOutput <= 16'sd0;
            outputValid <= 1'b0;
        end else begin
            outputValid <= 1'b0;

            if (sampleEnable) begin
                integralAccumulator <= integralAccumulator + currentError;
                previousError <= currentError;
                controlOutput <= saturate16(pidSum);

                outputValid <= 1'b1;
            end
        end
    end

endmodule

Verilog/29_SimpleMotorControl/sim/tb_simpleMotorControl.sv
`timescale 1ns/1ps

module tb_simpleMotorControl;

    logic sys_clk;
    logic sys_rst_n;

    logic sampleEnable;

    logic signed [15:0] setpoint;
    logic signed [15:0] measuredPosition;

    logic signed [15:0] kp;
    logic signed [15:0] ki;
    logic signed [15:0] kd;

    logic signed [15:0] controlOutput;
    logic outputValid;

    int sampleCount;

    pidMotorControl pidController (
        .sys_clk(sys_clk),
        .sys_rst_n(sys_rst_n),

        .sampleEnable(sampleEnable),

        .setpoint(setpoint),
        .measuredValue(measuredPosition),

        .kp(kp),
        .ki(ki),
        .kd(kd),

        .controlOutput(controlOutput),
        .outputValid(outputValid)
    );

    motorModel motorModel (
        .sys_clk(sys_clk),
        .sys_rst_n(sys_rst_n),

        .sampleEnable(sampleEnable),
        .command(controlOutput),

        .measuredPosition(measuredPosition)
    );

    initial begin
        sys_clk = 1'b0;
        forever #18.518 sys_clk = ~sys_clk; // 27 MHz clock
    end

    task runSample;
        begin
            @(negedge sys_clk);
            sampleEnable = 1'b1;

            @(negedge sys_clk);
            sampleEnable = 1'b0;

            wait (outputValid == 1'b1);
            @(posedge sys_clk);

            sampleCount = sampleCount + 1;

            $display(
                "sample=%0d setpoint=%0d measured=%0d error=%0d control=%0d velocity=%0d", sampleCount, setpoint, measuredPosition, 
                    pidController.currentError, controlOutput, motorModel.velocity);
        end
    endtask

    initial begin
        $dumpfile("sim/tb_simpleMotorControl.vcd");
        $dumpvars(0, tb_simpleMotorControl);

        sys_rst_n = 1'b0;
        sampleEnable = 1'b0;
        sampleCount = 0;

        setpoint = 16'sd0;

        kp = 16'sd0;
        ki = 16'sd0;
        kd = 16'sd0;

        #200;
        sys_rst_n = 1'b1;

        // PID gains: kp = 0.50, ki = 0.02, kd = 0.25
        kp = 16'sh0080;
        ki = 16'sh0005;
        kd = 16'sh0040;

        // Step command: Target position = +10.0
        setpoint = 16'sh0A00;

        // Let the closed-loop system respond to the step input
        repeat (120) begin
            runSample();
        end

        // Reverse direction: Target position = -5.0
        setpoint = -16'sd1280;

        repeat (120) begin
            runSample();
        end

        // Return to zero
        setpoint = 16'sd0;

        repeat (120) begin
            runSample();
        end

        repeat (8) @(posedge sys_clk);

        $finish;
    end

endmodule

Verilog/29_SimpleMotorControl/sim/tb_simpleMotorControl.vcd
$date
	Sat Jul 11 13:46:31 2026
$end
$version
	Icarus Verilog
$end
$timescale
	1ps
$end
$scope module tb_simpleMotorControl $end
$var wire 1 ! outputValid $end
$var wire 16 " measuredPosition [15:0] $end
$var wire 16 # controlOutput [15:0] $end
$var reg 16 $ kd [15:0] $end
$var reg 16 % ki [15:0] $end
$var reg 16 & kp [15:0] $end
$var reg 1 ' sampleEnable $end
$var reg 16 ( setpoint [15:0] $end
$var reg 1 ) sys_clk $end
$var reg 1 * sys_rst_n $end
$var integer 32 + sampleCount [31:0] $end
$scope module motorModel $end
$var wire 1 ' sampleEnable $end
$var wire 1 ) sys_clk $end
$var wire 1 * sys_rst_n $end
$var wire 32 , nextVelocity [31:0] $end
$var wire 32 - nextPosition [31:0] $end
$var wire 32 . damping [31:0] $end
$var wire 32 / commandExtended [31:0] $end
$var wire 16 0 command [15:0] $end
$var wire 32 1 acceleration [31:0] $end
$var reg 16 2 measuredPosition [15:0] $end
$var reg 32 3 position [31:0] $end
$var reg 32 4 velocity [31:0] $end
$scope function saturate16 $end
$upscope $end
$upscope $end
$scope module pidController $end
$var wire 16 5 kd [15:0] $end
$var wire 16 6 ki [15:0] $end
$var wire 16 7 kp [15:0] $end
$var wire 16 8 measuredValue [15:0] $end
$var wire 1 ' sampleEnable $end
$var wire 16 9 setpoint [15:0] $end
$var wire 1 ) sys_clk $end
$var wire 1 * sys_rst_n $end
$var wire 32 : proportionalTerm [31:0] $end
$var wire 32 ; proportionalProduct [31:0] $end
$var wire 32 < pidSum [31:0] $end
$var wire 32 = integralTerm [31:0] $end
$var wire 48 > integralProduct [47:0] $end
$var wire 16 ? errorDelta [15:0] $end
$var wire 32 @ derivativeTerm [31:0] $end
$var wire 32 A derivativeProduct [31:0] $end
$var wire 16 B currentError [15:0] $end
$var reg 16 C controlOutput [15:0] $end
$var reg 32 D integralAccumulator [31:0] $end
$var reg 1 ! outputValid $end
$var reg 16 E previousError [15:0] $end
$scope function saturate16 $end
$upscope $end
$upscope $end
$scope task runSample $end
$upscope $end
$upscope $end
$enddefinitions $end
$comment Show the parameter values. $end
$dumpall
$end
#0
$dumpvars
b0 E
b0 D
b0 C
b0 B
b0 A
b0 @
b0 ?
b0 >
b0 =
b0 <
b0 ;
b0 :
b0 9
b0 8
b0 7
b0 6
b0 5
b0 4
b0 3
b0 2
b0 1
b0 0
b0 /
b0 .
b0 -
b0 ,
b0 +
0*
0)
b0 (
0'
b0 &
b0 %
b0 $
b0 #
b0 "
0!
$end
#18518
1)
#37036
0)
#55554
1)
#74072
0)
#92590
1)
#111108
0)
#129626
1)
#148144
0)
#166662
1)
#185180
0)
#200000
b1010000000 @
b11110000000 <
b10100000000 :
b101000000000000000 A
b101000000000 ?
b1010000000000000000 ;
b101000000000 B
b101000000000 (
b101000000000 9
b1000000 $
b1000000 5
b101 %
b101 6
b10000000 &
b10000000 7
1*
#203698
1)
#222216
1'
0)
#240734
b1111 -
b110010 =
b11110000 ,
b10100110010 <
b0 @
1!
b11110000000 1
b11110000000 /
b11110000000 #
b11110000000 0
b11110000000 C
b0 A
b0 ?
b101000000000 E
b11001000000000 >
b101000000000 D
1)
#259252
0'
0)
#277770
0!
b1 +
1)
#296288
1'
0)
#314806
b1100100 =
b11111111111111111111111111111100 @
b10101011000 <
b10011111000 :
b11110 .
b11111111111111111111110001000000 A
b1111111111110001 ?
b1001111100010000000 ;
b100111110001 B
b1111 "
b1111 2
b1111 8
b101000 -
b1111 3
b110010010 ,
b11110000 4
1!
b10100010100 1
b10100110010 /
b10100110010 #
b10100110010 0
b10100110010 C
b110010000000000 >
b1010000000000 D
1)
#333324
0'
0)
#351842
0!
b10 +
1)
#370360
1'
0)
#388878
b10010101 =
b10011101100 :
b110010 .
b10101111010 <
b11111111111111111111111111111001 @
b1001110110000000000 ;
b100111011000 B
b101000 "
b101000 2
b101000 8
b1001011 -
b101000 3
b1000110110 ,
b110010010 4
1!
b10100100110 1
b10101011000 /
b10101011000 #
b10101011000 0
b10101011000 C
b11111111111111111111100111000000 A
b1111111111100111 ?
b100111110001 E
b1001010110110101 >
b1110111110001 D
1)
#407396
0'
0)
#425914
0!
b11 +
1)
#444432
1'
0)
#462950
b11000110 =
b10011011010 :
b1000110 .
b10110010111 <
b11111111111111111111111111110111 @
b1001101101010000000 ;
b100110110101 B
b1001011 "
b1001011 2
b1001011 8
b1111000 -
b1001011 3
b1011011100 ,
b1000110110 4
1!
b10100110100 1
b10101111010 /
b10101111010 #
b10101111010 0
b10101111010 C
b11111111111111111111011101000000 A
b1111111111011101 ?
b100111011000 E
b1100011011101101 >
b10011111001001 D
1)
#481468
0'
0)
#499986
0!
b100 +
1)
#518504
1'
0)
#537022
b11110111 =
b10011000100 :
b1011011 .
b10110101111 <
b11111111111111111111111111110100 @
b1001100010000000000 ;
b100110001000 B
b1111000 "
b1111000 2
b1111000 8
b10110000 -
b1111000 3
b1110000011 ,
b1011011100 4
1!
b10100111100 1
b10110010111 /
b10110010111 #
b10110010111 0
b10110010111 C
b11111111111111111111010011000000 A
b1111111111010011 ?
b100110110101 E
b1111011101110110 >
b11000101111110 D
1)
#555540
0'
0)
#574058
0!
b101 +
1)
#592576
1'
0)
#611094
b100100111 =
b10010101000 :
b1110000 .
b10111000001 <
b11111111111111111111111111110010 @
b1001010100000000000 ;
b100101010000 B
b10110000 "
b10110000 2
b10110000 8
b11110010 -
b10110000 3
b10000101010 ,
b1110000011 4
1!
b10100111111 1
b10110101111 /
b10110101111 #
b10110101111 0
b10110101111 C
b11111111111111111111001000000000 A
b1111111111001000 ?
b100110001000 E
b10010011100011110 >
b11101100000110 D
1)
#629612
0'
0)
#648130
0!
b110 +
1)
#666648
1'
0)
#685166
b101010101 =
b10010000111 :
b10000101 .
b10111001011 <
b11111111111111111111111111101111 @
b1001000011100000000 ;
b100100001110 B
b11110010 "
b11110010 2
b11110010 8
b100111111 -
b11110010 3
b10011010001 ,
b10000101010 4
1!
b10100111100 1
b10111000001 /
b10111000001 #
b10111000001 0
b10111000001 C
b11111111111111111110111110000000 A
b1111111110111110 ?
b100101010000 E
b10101010110101110 >
b100010001010110 D
1)
#703684
0'
0)
#722202
0!
b111 +
1)
#740720
1'
0)
#759238
b110000010 =
b10001100000 :
b10011010 .
b10111001110 <
b11111111111111111111111111101100 @
b1000110000010000000 ;
b100011000001 B
b100111111 "
b100111111 2
b100111111 8
b110010110 -
b100111111 3
b10101110111 ,
b10011010001 4
1!
b10100110001 1
b10111001011 /
b10111001011 #
b10111001011 0
b10111001011 C
b11111111111111111110110011000000 A
b1111111110110011 ?
b100100001110 E
b11000001011110100 >
b100110101100100 D
1)
#777756
0'
0)
#796274
0!
b1000 +
1)
#814792
1'
0)
#833310
b110101110 =
b10000110101 :
b10101110 .
b10111001101 <
b11111111111111111111111111101010 @
b1000011010100000000 ;
b100001101010 B
b110010110 "
b110010110 2
b110010110 8
b111110111 -
b110010110 3
b11000011011 ,
b10101110111 4
1!
b10100100000 1
b10111001110 /
b10111001110 #
b10111001110 0
b10111001110 C
b11111111111111111110101001000000 A
b1111111110101001 ?
b100011000001 E
b11010111010111001 >
b101011000100101 D
1)
#851828
0'
0)
#870346
0!
b1001 +
1)
#888864
1'
0)
#907382
b111011000 =
b10000000100 :
b11000011 .
b10111000011 <
b11111111111111111111111111100111 @
b1000000010010000000 ;
b100000001001 B
b111110111 "
b111110111 2
b111110111 8
b1001100010 -
b111110111 3
b11010111100 ,
b11000011011 4
1!
b10100001010 1
b10111001101 /
b10111001101 #
b10111001101 0
b10111001101 C
b11111111111111111110011111000000 A
b1111111110011111 ?
b100001101010 E
b11101100011001011 >
b101111010001111 D
1)
#925900
0'
0)
#944418
0!
b1010 +
1)
#962936
1'
0)
#981454
b1000000000 =
b1111001111 :
b11010111 .
b10110110100 <
b11111111111111111111111111100101 @
b111100111100000000 ;
b11110011110 B
b1001100010 "
b1001100010 2
b1001100010 8
b1011010111 -
b1001100010 3
b11101011001 ,
b11010111100 4
1!
b10011101100 1
b10111000011 /
b10111000011 #
b10111000011 0
b10111000011 C
b11111111111111111110010101000000 A
b1111111110010101 ?
b100000001001 E
b100000000011111000 >
b110011010011000 D
1)
#999972
0'
0)
#1018490
0!
b1011 +
1)
#1037008
1'
0)
#1055526
b1000100111 =
b1110010100 :
b11101011 .
b10110011101 <
b11111111111111111111111111100010 @
b111001010010000000 ;
b11100101001 B
b1011010111 "
b1011010111 2
b1011010111 8
b1101010110 -
b1011010111 3
b11111110010 ,
b11101011001 4
1!
b10011001001 1
b10110110100 /
b10110110100 #
b10110110100 0
b10110110100 C
b11111111111111111110001011000000 A
b1111111110001011 ?
b11110011110 E
b100010011100001110 >
b110111000110110 D
1)
#1074044
0'
0)
#1092562
0!
b1100 +
1)
#1111080
1'
0)
#1129598
b1001001010 =
b1101010101 :
b11111110 .
b10101111111 <
b11111111111111111111111111100000 @
b110101010100000000 ;
b11010101010 B
b1101010110 "
b1101010110 2
b1101010110 8
b1111011110 -
b1101010110 3
b100010000101 ,
b11111110010 4
1!
b10010011111 1
b10110011101 /
b10110011101 #
b10110011101 0
b10110011101 C
b11111111111111111110000001000000 A
b1111111110000001 ?
b11100101001 E
b100100101011011011 >
b111010101011111 D
1)
#1148116
0'
0)
#1166634
0!
b1101 +
1)
#1185152
1'
0)
#1203670
b1001101100 =
b1100010001 :
b100010000 .
b10101011011 <
b11111111111111111111111111011110 @
b110001000100000000 ;
b11000100010 B
b1111011110 "
b1111011110 2
b1111011110 8
b10001101111 -
b1111011110 3
b100100010010 ,
b100010000101 4
1!
b10001101111 1
b10101111111 /
b10101111111 #
b10101111111 0
b10101111111 C
b11111111111111111101111000000000 A
b1111111101111000 ?
b11010101010 E
b100110110000101101 >
b111110000001001 D
1)
#1222188
0'
0)
#1240706
0!
b1110 +
1)
#1259224
1'
0)
#1277742
b1010001010 =
b1011001000 :
b100100010 .
b10100101101 <
b11111111111111111111111111011011 @
b101100100010000000 ;
b10110010001 B
b10001101111 "
b10001101111 2
b10001101111 8
b10100001000 -
b10001101111 3
b100110011001 ,
b100100010010 4
1!
b10000111001 1
b10101011011 /
b10101011011 #
b10101011011 0
b10101011011 C
b11111111111111111101101111000000 A
b1111111101101111 ?
b11000100010 E
b101000101011010111 >
b1000001000101011 D
1)
#1296260
0'
0)
#1314778
0!
b1111 +
1)
#1333296
1'
0)
#1351814
b1010100110 =
b1001111100 :
b100110011 .
b10011111011 <
b11111111111111111111111111011001 @
b100111110000000000 ;
b10011111000 B
b10100001000 "
b10100001000 2
b10100001000 8
b10110101001 -
b10100001000 3
b101000011000 ,
b100110011001 4
1!
b1111111010 1
b10100101101 /
b10100101101 #
b10100101101 0
b10100101101 C
b11111111111111111101100111000000 A
b1111111101100111 ?
b10110010001 E
b101010011010101100 >
b1000011110111100 D
1)
#1370332
0'
0)
#1388850
0!
b10000 +
1)
#1407368
1'
0)
#1425886
b1010111111 =
b1000101011 :
b101000011 .
b10011000001 <
b11111111111111111111111111010111 @
b100010101110000000 ;
b10001010111 B
b10110101001 "
b10110101001 2
b10110101001 8
b11001010001 -
b10110101001 3
b101010001111 ,
b101000011000 4
1!
b1110111000 1
b10011111011 /
b10011111011 #
b10011111011 0
b10011111011 C
b11111111111111111101011111000000 A
b1111111101011111 ?
b10011111000 E
b101011111110000100 >
b1000110010110100 D
1)
#1444404
0'
0)
#1462922
0!
b10001 +
1)
#1481440
1'
0)
#1499958
b1011010101 =
b111010111 :
b101010001 .
b10010000010 <
b11111111111111111111111111010110 @
b11101011110000000 ;
b1110101111 B
b11001010001 "
b11001010001 2
b11001010001 8
b11100000000 -
b11001010001 3
b101011111101 ,
b101010001111 4
1!
b1101110000 1
b10011000001 /
b10011000001 #
b10011000001 0
b10011000001 C
b11111111111111111101011000000000 A
b1111111101011000 ?
b10001010111 E
b101101010100110111 >
b1001000100001011 D
1)
#1518476
0'
0)
#1536994
0!
b10010 +
1)
#1555512
1'
0)
#1574030
b1011100111 =
b110000000 :
b101011111 .
b10000111011 <
b11111111111111111111111111010100 @
b11000000000000000 ;
b1100000000 B
b11100000000 "
b11100000000 2
b11100000000 8
b11110110110 -
b11100000000 3
b101101100001 ,
b101011111101 4
1!
b1100100011 1
b10010000010 /
b10010000010 #
b10010000010 0
b10010000010 C
b11111111111111111101010001000000 A
b1111111101010001 ?
b1110101111 E
b101110011110100010 >
b1001010010111010 D
1)
#1592548
0'
0)
#1611066
0!
b10011 +
1)
#1629584
1'
0)
#1648102
b1011110110 =
b100100101 :
b101101100 .
b1111101101 <
b11111111111111111111111111010010 @
b10010010100000000 ;
b1001001010 B
b11110110110 "
b11110110110 2
b11110110110 8
b100001110001 -
b11110110110 3
b101110111010 ,
b101101100001 4
1!
b1011001111 1
b10000111011 /
b10000111011 #
b10000111011 0
b10000111011 C
b11111111111111111101001010000000 A
b1111111101001010 ?
b1100000000 E
b101111011010100010 >
b1001011110111010 D
1)
#1666620
0'
0)
#1685138
0!
b10100 +
1)
#1703656
1'
0)
#1722174
b1100000010 =
b11000111 :
b101110111 .
b1110011010 <
b11111111111111111111111111010001 @
b1100011110000000 ;
b110001111 B
b100001110001 "
b100001110001 2
b100001110001 8
b100100110001 -
b100001110001 3
b110000001000 ,
b101110111010 4
1!
b1001110110 1
b1111101101 /
b1111101101 #
b1111101101 0
b1111101101 C
b11111111111111111101000101000000 A
b1111111101000101 ?
b1001001010 E
b110000001000010100 >
b1001101000000100 D
1)
#1740692
0'
0)
#1759210
0!
b10101 +
1)
#1777728
1'
0)
#1796246
b1100001001 =
b1100111 :
b110000001 .
b1101000000 <
b11111111111111111111111111010000 @
b110011110000000 ;
b11001111 B
b100100110001 "
b100100110001 2
b100100110001 8
b100111110101 -
b100100110001 3
b110001001011 ,
b110000001000 4
1!
b1000011001 1
b1110011010 /
b1110011010 #
b1110011010 0
b1110011010 C
b11111111111111111101000000000000 A
b1111111101000000 ?
b110001111 E
b110000100111011111 >
b1001101110010011 D
1)
#1814764
0'
0)
#1833282
0!
b10110 +
1)
#1851800
1'
0)
#1870318
b1100001101 =
b101 :
b110001001 .
b1011100001 <
b11111111111111111111111111001111 @
b10110000000 ;
b1011 B
b100111110101 "
b100111110101 2
b100111110101 8
b101010111101 -
b100111110101 3
b110010000001 ,
b110001001011 4
1!
b110110111 1
b1101000000 /
b1101000000 #
b1101000000 0
b1101000000 C
b11111111111111111100111100000000 A
b1111111100111100 ?
b11001111 E
b110000110111101010 >
b1001110001100010 D
1)
#1888836
0'
0)
#1907354
0!
b10111 +
1)
#1925872
1'
0)
#1944390
b1100001110 =
b11111111111111111111111110100001 :
b110010000 .
b1001111101 <
b11111111111111111111111111001110 @
b11111111111111111010000110000000 ;
b1111111101000011 B
b101010111101 "
b101010111101 2
b101010111101 8
b101110000111 -
b101010111101 3
b110010101011 ,
b110010000001 4
1!
b101010001 1
b1011100001 /
b1011100001 #
b1011100001 0
b1011100001 C
b11111111111111111100111000000000 A
b1111111100111000 ?
b1011 E
b110000111000100001 >
b1001110001101101 D
1)
#1962908
0'
0)
#1981426
0!
b11000 +
1)
#1999944
1'
0)
#2018462
b1100001010 =
b11111111111111111111111100111100 :
b110010101 .
b1000010011 <
b11111111111111111111111111001101 @
b11111111111111110011110010000000 ;
b1111111001111001 B
b101110000111 "
b101110000111 2
b101110000111 8
b110001010011 -
b101110000111 3
b110011001000 ,
b110010101011 4
1!
b11101000 1
b1001111101 /
b1001111101 #
b1001111101 0
b1001111101 C
b11111111111111111100110110000000 A
b1111111100110110 ?
b1111111101000011 E
b110000101001110000 >
b1001101110110000 D
1)
#2036980
0'
0)
#2055498
0!
b11001 +
1)
#2074016
1'
0)
#2092534
b1100000010 =
b110100101 <
b11111111111111111111111011010110 :
b110011001 .
b11111111111111101101011010000000 ;
b1111110110101101 B
b110001010011 "
b110001010011 2
b110001010011 8
b110100100000 -
b110001010011 3
b110011010111 ,
b110011001000 4
1!
b1111010 1
b1000010011 /
b1000010011 #
b1000010011 0
b1000010011 C
b11111111111111111100110100000000 A
b1111111100110100 ?
b1111111001111001 E
b110000001011001101 >
b1001101000101001 D
1)
#2111052
0'
0)
#2129570
0!
b11010 +
1)
#2148088
1'
0)
#2166606
b1011110111 =
b11111111111111111111111001110000 :
b110011010 .
b100110011 <
b11111111111111111111111111001100 @
b11111111111111100111000000000000 ;
b1111110011100000 B
b110100100000 "
b110100100000 2
b110100100000 8
b110111101101 -
b110100100000 3
b110011011000 ,
b110011010111 4
1!
b1011 1
b110100101 /
b110100101 #
b110100101 0
b110100101 C
b11111111111111111100110011000000 A
b1111111100110011 ?
b1111110110101101 E
b101111011100101110 >
b1001011111010110 D
1)
#2185124
0'
0)
#2203642
0!
b11011 +
1)
#2222160
1'
0)
#2240678
b1011100111 =
b10111100 <
b11111111111111111111111000001001 :
b110011011 .
b11111111111111100000100110000000 ;
b1111110000010011 B
b110111101101 "
b110111101101 2
b110111101101 8
b111010111001 -
b110111101101 3
b110011001011 ,
b110011011000 4
1!
b11111111111111111111111110011000 1
b100110011 /
b100110011 #
b100110011 0
b100110011 C
b11111111111111111100110011000000 A
b1111111100110011 ?
b1111110011100000 E
b101110011110001110 >
b1001010010110110 D
1)
#2259196
0'
0)
#2277714
0!
b11100 +
1)
#2296232
1'
0)
#2314750
b1011010011 =
b11111111111111111111110110100011 :
b110011001 .
b1000011 <
b11111111111111111111111111001101 @
b11111111111111011010001110000000 ;
b1111101101000111 B
b111010111001 "
b111010111001 2
b111010111001 8
b111110000011 -
b111010111001 3
b110010101111 ,
b110011001011 4
1!
b11111111111111111111111100100011 1
b10111100 /
b10111100 #
b10111100 0
b10111100 C
b11111111111111111100110100000000 A
b1111111100110100 ?
b1111110000010011 E
b101101001111101101 >
b1001000011001001 D
1)
#2333268
0'
0)
#2351786
0!
b11101 +
1)
#2370304
1'
0)
#2388822
b1010111100 =
b11111111111111111111111111000111 <
b11111111111111111111110100111110 :
b110010101 .
b11111111111111010011111010000000 ;
b1111101001111101 B
b111110000011 "
b111110000011 2
b111110000011 8
b1000001001011 -
b111110000011 3
b110010000100 ,
b110010101111 4
1!
b11111111111111111111111010101110 1
b1000011 /
b1000011 #
b1000011 0
b1000011 C
b11111111111111111100110110000000 A
b1111111100110110 ?
b1111101101000111 E
b101011110001010000 >
b1000110000010000 D
1)
#2407340
0'
0)
#2425858
0!
b11110 +
1)
#2444376
1'
0)
#2462894
b1010100000 =
b11111111111111111111110011011010 :
b110010000 .
b11111111111111111111111101001000 <
b11111111111111111111111111001110 @
b11111111111111001101101010000000 ;
b1111100110110101 B
b1000001001011 "
b1000001001011 2
b1000001001011 8
b1000100001111 -
b1000001001011 3
b110001001010 ,
b110010000100 4
1!
b11111111111111111111111000110111 1
b11111111111111111111111111000111 /
b1111111111000111 #
b1111111111000111 0
b1111111111000111 C
b11111111111111111100111000000000 A
b1111111100111000 ?
b1111101001111101 E
b101010000011000001 >
b1000011010001101 D
1)
#2481412
0'
0)
#2499930
0!
b11111 +
1)
#2518448
1'
0)
#2536966
b1010000001 =
b11111111111111111111110001111000 :
b110001001 .
b11111111111111111111111011001000 <
b11111111111111111111111111001111 @
b11111111111111000111100010000000 ;
b1111100011110001 B
b1000100001111 "
b1000100001111 2
b1000100001111 8
b1000111001111 -
b1000100001111 3
b110000000001 ,
b110001001010 4
1!
b11111111111111111111110110111111 1
b11111111111111111111111101001000 /
b1111111101001000 #
b1111111101001000 0
b1111111101001000 C
b11111111111111111100111100000000 A
b1111111100111100 ?
b1111100110110101 E
b101000000101001010 >
b1000000001000010 D
1)
#2555484
0'
0)
#2574002
0!
b100000 +
1)
#2592520
1'
0)
#2611038
b1001011101 =
b11111111111111111111110000011000 :
b110000000 .
b11111111111111111111111001000101 <
b11111111111111111111111111010000 @
b11111111111111000001100010000000 ;
b1111100000110001 B
b1000111001111 "
b1000111001111 2
b1000111001111 8
b1001010001001 -
b1000111001111 3
b101110101010 ,
b110000000001 4
1!
b11111111111111111111110101001000 1
b11111111111111111111111011001000 /
b1111111011001000 #
b1111111011001000 0
b1111111011001000 C
b11111111111111111101000000000000 A
b1111111101000000 ?
b1111100011110001 E
b100101110111111111 >
b111100100110011 D
1)
#2629556
0'
0)
#2648074
0!
b100001 +
1)
#2666592
1'
0)
#2685110
b1000110110 =
b11111111111111111111101110111011 :
b101110101 .
b11111111111111111111110111000010 <
b11111111111111111111111111010001 @
b11111111111110111011101110000000 ;
b1111011101110111 B
b1001010001001 "
b1001010001001 2
b1001010001001 8
b1001100111101 -
b1001010001001 3
b101101000100 ,
b101110101010 4
1!
b11111111111111111111110011010000 1
b11111111111111111111111001000101 /
b1111111001000101 #
b1111111001000101 0
b1111111001000101 C
b11111111111111111101000110000000 A
b1111111101000110 ?
b1111100000110001 E
b100011011011110100 >
b111000101100100 D
1)
#2703628
0'
0)
#2722146
0!
b100010 +
1)
#2740664
1'
0)
#2759182
b1000001100 =
b11111111111111111111101101100001 :
b101101000 .
b11111111111111111111110101000000 <
b11111111111111111111111111010011 @
b11111111111110110110000110000000 ;
b1111011011000011 B
b1001100111101 "
b1001100111101 2
b1001100111101 8
b1001111101001 -
b1001100111101 3
b101011001111 ,
b101101000100 4
1!
b11111111111111111111110001011010 1
b11111111111111111111110111000010 /
b1111110111000010 #
b1111110111000010 0
b1111110111000010 C
b11111111111111111101001100000000 A
b1111111101001100 ?
b1111011101110111 E
b100000110001000111 >
b110100011011011 D
1)
#2777700
0'
0)
#2796218
0!
b100011 +
1)
#2814736
1'
0)
#2833254
b111011110 =
b11111111111111111111101100001011 :
b101011001 .
b11111111111111111111110010111110 <
b11111111111111111111111111010101 @
b11111111111110110000101110000000 ;
b1111011000010111 B
b1001111101001 "
b1001111101001 2
b1001111101001 8
b1010010001101 -
b1001111101001 3
b101001001011 ,
b101011001111 4
1!
b11111111111111111111101111100111 1
b11111111111111111111110101000000 /
b1111110101000000 #
b1111110101000000 0
b1111110101000000 C
b11111111111111111101010100000000 A
b1111111101010100 ?
b1111011011000011 E
b11101111000010110 >
b101111110011110 D
1)
#2851772
0'
0)
#2870290
0!
b100100 +
1)
#2888808
1'
0)
#2907326
b110101100 =
b11111111111111111111101010111001 :
b101001001 .
b11111111111111111111110000111100 <
b11111111111111111111111111010111 @
b11111111111110101011100110000000 ;
b1111010101110011 B
b1010010001101 "
b1010010001101 2
b1010010001101 8
b1010100101000 -
b1010010001101 3
b100110111001 ,
b101001001011 4
1!
b11111111111111111111101101110101 1
b11111111111111111111110010111110 /
b1111110010111110 #
b1111110010111110 0
b1111110010111110 C
b11111111111111111101011100000000 A
b1111111101011100 ?
b1111011000010111 E
b11010110010001001 >
b101010110110101 D
1)
#2925844
0'
0)
#2944362
0!
b100101 +
1)
#2962880
1'
0)
#2981398
b101110111 =
b11111111111111111111101001101100 :
b100110111 .
b11111111111111111111101110111100 <
b11111111111111111111111111011001 @
b11111111111110100110110000000000 ;
b1111010011011000 B
b1010100101000 "
b1010100101000 2
b1010100101000 8
b1010110111001 -
b1010100101000 3
b100100011001 ,
b100110111001 4
1!
b11111111111111111111101100000101 1
b11111111111111111111110000111100 /
b1111110000111100 #
b1111110000111100 0
b1111110000111100 C
b11111111111111111101100101000000 A
b1111111101100101 ?
b1111010101110011 E
b10111011111001000 >
b100101100101000 D
1)
#2999916
0'
0)
#3018434
0!
b100110 +
1)
#3036952
1'
0)
