Verilog/26_TinyCPU/tinyCpu/src/tinyCpu.sv
// 8-bit CPU

module tinyCpu (
    input logic sys_clk,
    input logic sys_rst_n,

    output logic halted,
    output logic [7:0] programCounter,
    output logic [15:0] currentInstruction,

    output logic [7:0] debugR0,
    output logic [7:0] debugR1,
    output logic [7:0] debugR2,
    output logic [7:0] debugR3,
    output logic [7:0] debugR4,
    output logic [7:0] debugR5,
    output logic [7:0] debugR6,
    output logic [7:0] debugR7,
    output logic [7:0] debugMem10
);

    // Map instructions to opcodes
    localparam logic [3:0] OP_NOP   = 4'h0;
    localparam logic [3:0] OP_ADD   = 4'h1;
    localparam logic [3:0] OP_SUB   = 4'h2;
    localparam logic [3:0] OP_AND   = 4'h3;
    localparam logic [3:0] OP_OR    = 4'h4;
    localparam logic [3:0] OP_ADDI  = 4'h5;
    localparam logic [3:0] OP_LOAD  = 4'h6;
    localparam logic [3:0] OP_STORE = 4'h7;
    localparam logic [3:0] OP_JUMP  = 4'h8;
    localparam logic [3:0] OP_HALT  = 4'hF;

    // Simulated memory
    logic [15:0] instructionMemory [0:255]; // Program storage
    logic [7:0] dataMemory [0:255];         // Load/store memory

    // CPU working registers (r0, r1... r7)
    logic [7:0] registerFile [0:7];         // r0 is forced to zero (RISC-V/MIPS) 
    // A zero register gives the CPU a permanent constant 0, simplifies hardware and instruction encoding

    // Arithmetic Instructions: [15:12] opcode, [11:9] rd, [8:6] rs1, [5:3] rs2, [2:0] unused
    // Immediate Instructions: [15:12] opcode, [11:9] rd, [8:6] rs1, [5:0] immediate
    // e.g. ADDI r1, r0, 5 -> r1 = r0 + 5
    logic [3:0] opcode;
    logic [2:0] rd;     // Destination register
    logic [2:0] rs1;    // Source register 1
    logic [2:0] rs2;    // Source register 2
    logic signed [5:0] immediate6;
    logic signed [7:0] signExtendedImmediate;
    logic [7:0] address8;

    logic [5:0] storeAddress6;
    assign storeAddress6 = currentInstruction[5:0];

    // Fetch
    assign currentInstruction = instructionMemory[programCounter];

    // Decode
    // CPU can't understand ADD r3, r1, r2 -> ADD is opcode, leftmost 3 bits
    // Decoder converts bits into:
    assign opcode = currentInstruction[15:12];
    assign rd = currentInstruction[11:9];
    assign rs1 = currentInstruction[8:6];
    assign rs2 = currentInstruction[5:3];

    // ADDI uses 6-bit signed immediate, but CPU registers are 8 bits
    // 6-bit immediate is extended to 8 bits while preserving the sign
    assign immediate6 = currentInstruction[5:0];                        // Lower 6 bits of currentInstruction
    assign signExtendedImmediate = {{2{immediate6[5]}}, immediate6};    // Repeat immediate6[5] two times
    // 000101 -> immediate6[5] = 0 -> {2{0}} = 00 -> signExtendedImmediate = 00_000101 = 00000101 = +5
    // 111111 -> immediate6[5] = 1 -> {2{1}} = 11 -> signExtendedImmediate = 11_111111 = 11111111 = -1

    assign address8 = currentInstruction[7:0];  // Extracts lower 8 bits of the instruction as an address
    // if 0001_0000 -> 0x10 -> JUMP -> programCounter = address8 -> if address8 = 8'd20 => instructionMemory[20]

    // GTKWave Debug
    assign debugR0 = registerFile[0];
    assign debugR1 = registerFile[1];
    assign debugR2 = registerFile[2];
    assign debugR3 = registerFile[3];
    assign debugR4 = registerFile[4];
    assign debugR5 = registerFile[5];
    assign debugR6 = registerFile[6];
    assign debugR7 = registerFile[7];

    assign debugMem10 = dataMemory[8'h10];

    integer i;

    always_ff @(posedge sys_clk or negedge sys_rst_n) begin
        if (!sys_rst_n) begin
            programCounter <= 8'd0;
            halted <= 1'b0;

            for (i = 0; i < 8; i = i + 1) begin
                registerFile[i] <= 8'd0;
            end

            for (i = 0; i < 256; i = i + 1) begin
                dataMemory[i] <= 8'd0;
            end
        end else begin
            if (!halted) begin
                case (opcode)
                    OP_NOP: begin
                        programCounter <= programCounter + 8'd1;
                    end

                    OP_ADD: begin
                        if (rd != 3'd0) begin
                            registerFile[rd] <= registerFile[rs1] + registerFile[rs2];
                        end

                        programCounter <= programCounter + 8'd1;
                    end

                    OP_SUB: begin
                        if (rd != 3'd0) begin
                            registerFile[rd] <= registerFile[rs1] - registerFile[rs2];
                        end

                        programCounter <= programCounter + 8'd1;
                    end

                    OP_AND: begin
                        if (rd != 3'd0) begin
                            registerFile[rd] <= registerFile[rs1] & registerFile[rs2];
                        end

                        programCounter <= programCounter + 8'd1;
                    end

                    OP_OR: begin
                        if (rd != 3'd0) begin
                            registerFile[rd] <= registerFile[rs1] | registerFile[rs2];
                        end

                        programCounter <= programCounter + 8'd1;
                    end

                    OP_ADDI: begin
                        if (rd != 3'd0) begin
                            registerFile[rd] <= registerFile[rs1] + signExtendedImmediate;
                        end

                        programCounter <= programCounter + 8'd1;
                    end

                    OP_LOAD: begin
                        if (rd != 3'd0) begin
                            registerFile[rd] <= dataMemory[address8];
                        end

                        programCounter <= programCounter + 8'd1;
                    end

                    OP_STORE: begin
                        dataMemory[{2'b00, storeAddress6}] <= registerFile[rs1];

                        programCounter <= programCounter + 8'd1;
                    end

                    // PC = 5, instructionMemory[5] -> JUMP 12 -> After the clock edge -> PC = 12, instructionMemory[12]
                    OP_JUMP: begin
                        programCounter <= address8;
                    end

                    OP_HALT: begin
                        halted <= 1'b1;
                        programCounter <= programCounter;
                    end

                    default: begin
                        halted <= 1'b1;
                    end
                endcase

                // Keep r0 hardwired to zero
                registerFile[0] <= 8'd0;
            end
        end
    end

endmodule

Verilog/26_TinyCPU/sim/tb_tinyCpu.sv
`timescale 1ns/1ps

module tb_tinyCpu;

    logic sys_clk;
    logic sys_rst_n;

    logic halted;
    logic [7:0] programCounter;
    logic [15:0] currentInstruction;

    localparam logic [3:0] OP_NOP   = 4'h0;
    localparam logic [3:0] OP_ADD   = 4'h1;
    localparam logic [3:0] OP_SUB   = 4'h2;
    localparam logic [3:0] OP_AND   = 4'h3;
    localparam logic [3:0] OP_OR    = 4'h4;
    localparam logic [3:0] OP_ADDI  = 4'h5;
    localparam logic [3:0] OP_LOAD  = 4'h6;
    localparam logic [3:0] OP_STORE = 4'h7;
    localparam logic [3:0] OP_JUMP  = 4'h8;
    localparam logic [3:0] OP_HALT  = 4'hF;

    logic [7:0] debugR0;
    logic [7:0] debugR1;
    logic [7:0] debugR2;
    logic [7:0] debugR3;
    logic [7:0] debugR4;
    logic [7:0] debugR5;
    logic [7:0] debugR6;
    logic [7:0] debugR7;
    logic [7:0] debugMem10;

    tinyCpu dut (
        .sys_clk(sys_clk),
        .sys_rst_n(sys_rst_n),
        .halted(halted),
        .programCounter(programCounter),
        .currentInstruction(currentInstruction),

        .debugR0(debugR0),
        .debugR1(debugR1),
        .debugR2(debugR2),
        .debugR3(debugR3),
        .debugR4(debugR4),
        .debugR5(debugR5),
        .debugR6(debugR6),
        .debugR7(debugR7),
        .debugMem10(debugMem10)
    );

    initial begin
        sys_clk = 1'b0;
        forever #18.518 sys_clk = ~sys_clk; // 27 MHz clock
    end

    // Encode R-type instructions
    function automatic logic [15:0] encodeR(input logic [3:0] opcode, input logic [2:0] rd, input logic [2:0] rs1, input logic [2:0] rs2);
        begin
            encodeR = {opcode, rd, rs1, rs2, 3'b000};
        end
    endfunction

    // Encode ADDI
    function automatic logic [15:0] encodeAddi(input logic [2:0] rd, input logic [2:0] rs1, input logic signed [5:0] imm6);
        begin
            encodeAddi = {OP_ADDI, rd, rs1, imm6};
        end
    endfunction

    // Encode LOAD
    function automatic logic [15:0] encodeLoad(input logic [2:0] rd, input logic [7:0] addr);
        begin
            encodeLoad = {OP_LOAD, rd, 1'b0, addr};
        end
    endfunction

    // Encode STORE
    function automatic logic [15:0] encodeStore(input logic [2:0] rs1, input logic [7:0] addr);
        begin
            encodeStore = {OP_STORE, 3'b000, rs1, addr[5:0]};
        end
    endfunction

    // This STORE encoding keeps rs1 in bits [8:6].
    //
    // Because the instruction is only 16 bits, this version uses a 6-bit address
    // for STORE. That is enough for this project.
    //
    // LOAD uses an 8-bit address.
    // This asymmetry is not ideal ISA design, but it keeps the decoder simple.

    function automatic logic [15:0] encodeJump(input logic [7:0] addr);
        begin
            encodeJump = {OP_JUMP, 4'b0000, addr};
        end
    endfunction

    function automatic logic [15:0] encodeHalt;
        begin
            encodeHalt = {OP_HALT, 12'd0};
        end
    endfunction

    task checkRegister(input logic [2:0] regIndex, input logic [7:0] expectedValue);
        begin
            if (dut.registerFile[regIndex] !== expectedValue) begin
                $display(
                    "ERROR: r%0d expected %0d / 0x%02h, got %0d / 0x%02h", regIndex, expectedValue, expectedValue, dut.registerFile[regIndex], dut.registerFile[regIndex]);
            end else begin
                $display(
                    "PASS: r%0d = %0d / 0x%02h", regIndex, dut.registerFile[regIndex], dut.registerFile[regIndex]);
            end
        end
    endtask

    initial begin
        $dumpfile("sim/tb_tinyCpu.vcd");
        $dumpvars(0, tb_tinyCpu);

        sys_rst_n = 1'b0;

        // Program:
        // r1 = 5
        // r2 = 7
        // r3 = r1 + r2 = 12
        // mem[0x10] = r3
        // r4 = mem[0x10] = 12
        // r5 = r4 - r1 = 7
        // r6 = r5 & r2 = 7
        // r7 = r6 | r1 = 7
        // halt

        dut.instructionMemory[8'd0] = encodeAddi(3'd1, 3'd0, 6'sd5);
        dut.instructionMemory[8'd1] = encodeAddi(3'd2, 3'd0, 6'sd7);
        dut.instructionMemory[8'd2] = encodeR(OP_ADD, 3'd3, 3'd1, 3'd2);
        dut.instructionMemory[8'd3] = encodeStore(3'd3, 8'h10);
        dut.instructionMemory[8'd4] = encodeLoad(3'd4, 8'h10);
        dut.instructionMemory[8'd5] = encodeR(OP_SUB, 3'd5, 3'd4, 3'd1);
        dut.instructionMemory[8'd6] = encodeR(OP_AND, 3'd6, 3'd5, 3'd2);
        dut.instructionMemory[8'd7] = encodeR(OP_OR, 3'd7, 3'd6, 3'd1);
        dut.instructionMemory[8'd8] = encodeHalt();

        #200;
        sys_rst_n = 1'b1;

        wait (halted == 1'b1);

        @(posedge sys_clk);

        $display("CPU halted.");
        $display("Final PC = %0d", programCounter);

        checkRegister(3'd0, 8'd0);
        checkRegister(3'd1, 8'd5);
        checkRegister(3'd2, 8'd7);
        checkRegister(3'd3, 8'd12);
        checkRegister(3'd4, 8'd12);
        checkRegister(3'd5, 8'd7);
        checkRegister(3'd6, 8'd7);
        checkRegister(3'd7, 8'd7);

        if (dut.dataMemory[8'h10] !== 8'd12) begin
            $display(
                "ERROR: mem[0x10] expected 12 / 0x0C, got %0d / 0x%02h",
                dut.dataMemory[8'h10],
                dut.dataMemory[8'h10]
            );
        end else begin
            $display("PASS: mem[0x10] = 12 / 0x0C");
        end

        repeat (4) @(posedge sys_clk);

        $finish;
    end

endmodule

Verilog/26_TinyCPU/sim/tb_tinyCpu.vcd
$date
	Sat Jul 11 00:34:03 2026
$end
$version
	Icarus Verilog
$end
$timescale
	1ps
$end
$scope module tb_tinyCpu $end
$var wire 8 ! programCounter [7:0] $end
$var wire 1 " halted $end
$var wire 8 # debugR7 [7:0] $end
$var wire 8 $ debugR6 [7:0] $end
$var wire 8 % debugR5 [7:0] $end
$var wire 8 & debugR4 [7:0] $end
$var wire 8 ' debugR3 [7:0] $end
$var wire 8 ( debugR2 [7:0] $end
$var wire 8 ) debugR1 [7:0] $end
$var wire 8 * debugR0 [7:0] $end
$var wire 8 + debugMem10 [7:0] $end
$var wire 16 , currentInstruction [15:0] $end
$var parameter 4 - OP_ADD $end
$var parameter 4 . OP_ADDI $end
$var parameter 4 / OP_AND $end
$var parameter 4 0 OP_HALT $end
$var parameter 4 1 OP_JUMP $end
$var parameter 4 2 OP_LOAD $end
$var parameter 4 3 OP_NOP $end
$var parameter 4 4 OP_OR $end
$var parameter 4 5 OP_STORE $end
$var parameter 4 6 OP_SUB $end
$var reg 1 7 sys_clk $end
$var reg 1 8 sys_rst_n $end
$scope function encodeAddi $end
$upscope $end
$scope function encodeHalt $end
$upscope $end
$scope function encodeJump $end
$upscope $end
$scope function encodeLoad $end
$upscope $end
$scope function encodeR $end
$upscope $end
$scope function encodeStore $end
$upscope $end
$scope module dut $end
$var wire 16 9 currentInstruction [15:0] $end
$var wire 8 : debugMem10 [7:0] $end
$var wire 8 ; debugR0 [7:0] $end
$var wire 8 < debugR1 [7:0] $end
$var wire 8 = debugR2 [7:0] $end
$var wire 8 > debugR3 [7:0] $end
$var wire 8 ? debugR4 [7:0] $end
$var wire 8 @ debugR5 [7:0] $end
$var wire 8 A debugR6 [7:0] $end
$var wire 8 B debugR7 [7:0] $end
$var wire 1 7 sys_clk $end
$var wire 1 8 sys_rst_n $end
$var wire 6 C storeAddress6 [5:0] $end
$var wire 8 D signExtendedImmediate [7:0] $end
$var wire 3 E rs2 [2:0] $end
$var wire 3 F rs1 [2:0] $end
$var wire 3 G rd [2:0] $end
$var wire 4 H opcode [3:0] $end
$var wire 6 I immediate6 [5:0] $end
$var wire 8 J address8 [7:0] $end
$var parameter 4 K OP_ADD $end
$var parameter 4 L OP_ADDI $end
$var parameter 4 M OP_AND $end
$var parameter 4 N OP_HALT $end
$var parameter 4 O OP_JUMP $end
$var parameter 4 P OP_LOAD $end
$var parameter 4 Q OP_NOP $end
$var parameter 4 R OP_OR $end
$var parameter 4 S OP_STORE $end
$var parameter 4 T OP_SUB $end
$var reg 1 " halted $end
$var reg 8 U programCounter [7:0] $end
$var integer 32 V i [31:0] $end
$upscope $end
$scope task checkRegister $end
$var reg 8 W expectedValue [7:0] $end
$var reg 3 X regIndex [2:0] $end
$upscope $end
$upscope $end
$enddefinitions $end
$comment Show the parameter values. $end
$dumpall
b10 T
b111 S
b100 R
b0 Q
b110 P
b1000 O
b1111 N
b11 M
b101 L
b1 K
b10 6
b111 5
b100 4
b0 3
b110 2
b1000 1
b1111 0
b11 /
b101 .
b1 -
$end
#0
$dumpvars
bx X
bx W
b100000000 V
b0 U
b101 J
b101 I
b101 H
b1 G
b0 F
b0 E
b101 D
b101 C
b0 B
b0 A
b0 @
b0 ?
b0 >
b0 =
b0 <
b0 ;
b0 :
b101001000000101 9
08
07
b101001000000101 ,
b0 +
b0 *
b0 )
b0 (
b0 '
b0 &
b0 %
b0 $
b0 #
0"
b0 !
$end
#18518
b100000000 V
17
#37036
07
#55554
b100000000 V
17
#74072
07
#92590
b100000000 V
17
#111108
07
#129626
b100000000 V
17
#148144
07
#166662
b100000000 V
17
#185180
07
#200000
18
#203698
b111 C
b10 G
b111 D
b111 I
b111 J
b101010000000111 ,
b101010000000111 9
b1 !
b1 U
b101 )
b101 <
17
#222216
07
#240734
b10000 C
b1 H
b11 G
b1 F
b10 E
b10000 D
b10000 I
b1010000 J
b1011001010000 ,
b1011001010000 9
b10 !
b10 U
b111 (
b111 =
17
#259252
07
#277770
b111 H
b0 G
b11 F
b11010000 J
b111000011010000 ,
b111000011010000 9
b11 !
b11 U
b1100 '
b1100 >
17
#296288
07
#314806
b110 H
b100 G
b0 F
b10000 J
b110100000010000 ,
b110100000010000 9
b100 !
b100 U
b1100 +
b1100 :
17
#333324
07
#351842
b1000 C
b10 H
b101 G
b100 F
b1 E
b1000 D
b1000 I
b1000 J
b10101100001000 ,
b10101100001000 9
b101 !
b101 U
b1100 &
b1100 ?
17
#370360
07
#388878
b10000 C
b11 H
b110 G
b101 F
b10 E
b10000 D
b10000 I
b1010000 J
b11110101010000 ,
b11110101010000 9
b110 !
b110 U
b111 %
b111 @
17
#407396
07
#425914
b1000 C
b100 H
b111 G
b110 F
b1 E
b1000 D
b1000 I
b10001000 J
b100111110001000 ,
b100111110001000 9
b111 !
b111 U
b111 $
b111 A
17
#444432
07
#462950
b0 C
b1111 H
b0 G
b0 F
b0 E
b0 D
b0 I
b0 J
b1111000000000000 ,
b1111000000000000 9
b1000 !
b1000 U
b111 #
b111 B
17
#481468
07
#499986
1"
17
#518504
07
#537022
b111 W
b111 X
17
