12_SyncFifo/syncFifo/src/syncFifo.sv
// Parameterized module, makes module reusable, can instantiate a different FIFO later
module syncFifo #(                      // Constants, compile-time
    parameter int DATA_WIDTH = 8,       
    parameter int DEPTH = 16,
    parameter int ADDR_WIDTH = 4
) (                                     // Ports
    input logic sys_clk,
    input logic sys_rst_n,

    input logic writeEnable,
    input logic [DATA_WIDTH-1:0] writeData,
    output logic full,

    input logic readEnable,
    output logic [DATA_WIDTH-1:0] readData,
    output logic empty,

    output logic [ADDR_WIDTH:0] count
);
    
    // logic [MSB_index:LSB_index] "variableName" [indexFirstAddress:indexLastAddress]
    logic [DATA_WIDTH-1:0] memory [0:DEPTH-1];  

    logic [ADDR_WIDTH-1:0] writePointer;
    logic [ADDR_WIDTH-1:0] readPointer;

    logic writeValid;
    logic readValid;

    assign full = (count == DEPTH);     // Combinational: updates when "count" changes
    assign empty = (count == 0);

    assign writeValid = writeEnable && !full;
    assign readValid = readEnable && !empty;

    always_ff @(posedge sys_clk or negedge sys_rst_n) begin     // Sequential: clock dependent
        if (!sys_rst_n) begin
            writePointer <= '0;
            readPointer <= '0;
            readData <= '0;
            count <= '0;
        end else begin
            if (writeValid) begin
                memory[writePointer] <= writeData;
                writePointer <= writePointer + 1'b1;
            end

            if (readValid) begin
                readData <= memory[readPointer];
                readPointer <= readPointer + 1'b1;
            end

            case ({writeValid, readValid})
                2'b10: begin
                    count <= count + 1'b1;
                end

                2'b01: begin
                    count <= count - 1'b1;
                end

                default: begin
                    count <= count;
                end
            endcase
        end
    end
endmodule

12_SyncFifo/sim/tb_syncFifo.sv
`timescale 1ns/1ps

module tb_syncFifo;

    logic sys_clk;
    logic sys_rst_n;

    logic writeEnable;
    logic [7:0] writeData;
    logic full;

    logic readEnable;
    logic [7:0] readData;
    logic empty;

    logic [4:0] count;

    syncFifo dut (
        .sys_clk(sys_clk),
        .sys_rst_n(sys_rst_n),
        .writeEnable(writeEnable),
        .writeData(writeData),
        .full(full),
        .readEnable(readEnable),
        .readData(readData),
        .empty(empty),
        .count(count)
    );

    initial begin
        sys_clk = 1'b0;
        forever #18.518 sys_clk = ~sys_clk;
    end

    task writeByte(input logic [7:0] dataByte);
        begin
            // Change inputs away from FIFO sampling edge.
            @(negedge sys_clk);

            // Request one FIFO write.
            writeData = dataByte;
            writeEnable = 1'b1;

            // FIFO samples writeEnable/writeData on next rising edge.

            @(negedge sys_clk);

            // End one-clock write pulse.
            writeEnable = 1'b0;
            writeData = 8'd0;
        end
    endtask

    task readByte;
        begin
            @(negedge sys_clk);
            readEnable = 1'b1;

            @(negedge sys_clk);
            readEnable = 1'b0;
        end
    endtask

    initial begin
        sys_rst_n = 1'b0;
        writeEnable = 1'b0;
        writeData = 8'd0;
        readEnable = 1'b0;

        #200;
        sys_rst_n = 1'b1;

        writeByte(8'h11);
        writeByte(8'h22);
        writeByte(8'h33);

        readByte();
        readByte();
        readByte();

        writeByte(8'hA0);
        writeByte(8'hA1);
        writeByte(8'hA2);
        writeByte(8'hA3);
        writeByte(8'hA4);
        writeByte(8'hA5);
        writeByte(8'hA6);
        writeByte(8'hA7);
        writeByte(8'hA8);
        writeByte(8'hA9);
        writeByte(8'hAA);
        writeByte(8'hAB);
        writeByte(8'hAC);
        writeByte(8'hAD);
        writeByte(8'hAE);
        writeByte(8'hAF);

        writeByte(8'hFF);

        readByte();
        readByte();
        readByte();
        readByte();

        @(negedge sys_clk);
        writeData = 8'h55;
        writeEnable = 1'b1;
        readEnable = 1'b1;

        @(negedge sys_clk);
        writeEnable = 1'b0;
        readEnable = 1'b0;
        writeData = 8'd0;

        #1000;
        $finish;
    end

    initial begin
        $dumpfile("sim/tb_syncFifo.vcd");
        $dumpvars(0, tb_syncFifo);
    end

endmodule

Verilog/12_SyncFifo/sim/tb_syncFifo.vcd
$date
	Mon Jun 29 01:20:24 2026
$end
$version
	Icarus Verilog
$end
$timescale
	1ps
$end
$scope module tb_syncFifo $end
$var wire 8 ! readData [7:0] $end
$var wire 1 " full $end
$var wire 1 # empty $end
$var wire 5 $ count [4:0] $end
$var reg 1 % readEnable $end
$var reg 1 & sys_clk $end
$var reg 1 ' sys_rst_n $end
$var reg 8 ( writeData [7:0] $end
$var reg 1 ) writeEnable $end
$scope module dut $end
$var wire 1 % readEnable $end
$var wire 1 * readValid $end
$var wire 1 & sys_clk $end
$var wire 1 ' sys_rst_n $end
$var wire 8 + writeData [7:0] $end
$var wire 1 ) writeEnable $end
$var wire 1 , writeValid $end
$var wire 1 " full $end
$var wire 1 # empty $end
$var parameter 32 - ADDR_WIDTH $end
$var parameter 32 . DATA_WIDTH $end
$var parameter 32 / DEPTH $end
$var reg 5 0 count [4:0] $end
$var reg 8 1 readData [7:0] $end
$var reg 4 2 readPointer [3:0] $end
$var reg 4 3 writePointer [3:0] $end
$upscope $end
$scope task readByte $end
$upscope $end
$scope task writeByte $end
$var reg 8 4 dataByte [7:0] $end
$upscope $end
$upscope $end
$enddefinitions $end
$comment Show the parameter values. $end
$dumpall
b10000 /
b1000 .
b100 -
$end
#0
$dumpvars
bx 4
b0 3
b0 2
b0 1
b0 0
0,
b0 +
0*
0)
b0 (
0'
0&
0%
b0 $
1#
0"
b0 !
$end
#18518
1&
#37036
0&
#55554
1&
#74072
0&
#92590
1&
#111108
0&
#129626
1&
#148144
0&
#166662
1&
#185180
0&
#200000
b10001 4
1'
#203698
1&
#222216
1,
1)
b10001 (
b10001 +
0&
#240734
0#
b1 $
b1 0
b1 3
1&
#259252
0,
b100010 4
b0 (
b0 +
0)
0&
#277770
1&
#296288
1,
1)
b100010 (
b100010 +
0&
#314806
b10 $
b10 0
b10 3
1&
#333324
0,
b110011 4
b0 (
b0 +
0)
0&
#351842
1&
#370360
1,
1)
b110011 (
b110011 +
0&
#388878
b11 $
b11 0
b11 3
1&
#407396
0,
b0 (
b0 +
0)
0&
#425914
1&
#444432
1*
1%
0&
#462950
b10 $
b10 0
b1 2
b10001 !
b10001 1
1&
#481468
0*
0%
0&
#499986
1&
#518504
1*
1%
0&
#537022
b1 $
b1 0
b10 2
b100010 !
b100010 1
1&
#555540
0*
0%
0&
#574058
1&
#592576
1*
1%
0&
#611094
0*
1#
b0 $
b0 0
b11 2
b110011 !
b110011 1
1&
#629612
b10100000 4
0%
0&
#648130
1&
#666648
1,
1)
b10100000 (
b10100000 +
0&
#685166
0#
b1 $
b1 0
b100 3
1&
#703684
0,
b10100001 4
b0 (
b0 +
0)
0&
#722202
1&
#740720
1,
1)
b10100001 (
b10100001 +
0&
#759238
b10 $
b10 0
b101 3
1&
#777756
0,
b10100010 4
b0 (
b0 +
0)
0&
#796274
1&
#814792
1,
1)
b10100010 (
b10100010 +
0&
#833310
b11 $
b11 0
b110 3
1&
#851828
0,
b10100011 4
b0 (
b0 +
0)
0&
#870346
1&
#888864
1,
1)
b10100011 (
b10100011 +
0&
#907382
b100 $
b100 0
b111 3
1&
#925900
0,
b10100100 4
b0 (
b0 +
0)
0&
#944418
1&
#962936
1,
1)
b10100100 (
b10100100 +
0&
#981454
b101 $
b101 0
b1000 3
1&
#999972
0,
b10100101 4
b0 (
b0 +
0)
0&
#1018490
1&
#1037008
1,
1)
b10100101 (
b10100101 +
0&
#1055526
b110 $
b110 0
b1001 3
1&
#1074044
0,
b10100110 4
b0 (
b0 +
0)
0&
#1092562
1&
#1111080
1,
1)
b10100110 (
b10100110 +
0&
#1129598
b111 $
b111 0
b1010 3
1&
#1148116
0,
b10100111 4
b0 (
b0 +
0)
0&
#1166634
1&
#1185152
1,
1)
b10100111 (
b10100111 +
0&
#1203670
b1000 $
b1000 0
b1011 3
1&
#1222188
0,
b10101000 4
b0 (
b0 +
0)
0&
#1240706
1&
#1259224
1,
1)
b10101000 (
b10101000 +
0&
#1277742
b1001 $
b1001 0
b1100 3
1&
#1296260
0,
b10101001 4
b0 (
b0 +
0)
0&
#1314778
1&
#1333296
1,
1)
b10101001 (
b10101001 +
0&
#1351814
b1010 $
b1010 0
b1101 3
1&
#1370332
0,
b10101010 4
b0 (
b0 +
0)
0&
#1388850
1&
#1407368
1,
1)
b10101010 (
b10101010 +
0&
#1425886
b1011 $
b1011 0
b1110 3
1&
#1444404
0,
b10101011 4
b0 (
b0 +
0)
0&
#1462922
1&
#1481440
1,
1)
b10101011 (
b10101011 +
0&
#1499958
b1100 $
b1100 0
b1111 3
1&
#1518476
0,
b10101100 4
b0 (
b0 +
0)
0&
#1536994
1&
#1555512
1,
1)
b10101100 (
b10101100 +
0&
#1574030
b1101 $
b1101 0
b0 3
1&
#1592548
0,
b10101101 4
b0 (
b0 +
0)
0&
#1611066
1&
#1629584
1,
1)
b10101101 (
b10101101 +
0&
#1648102
b1110 $
b1110 0
b1 3
1&
#1666620
0,
b10101110 4
b0 (
b0 +
0)
0&
#1685138
1&
#1703656
1,
1)
b10101110 (
b10101110 +
0&
#1722174
b1111 $
b1111 0
b10 3
1&
#1740692
0,
b10101111 4
b0 (
b0 +
0)
0&
#1759210
1&
#1777728
1,
1)
b10101111 (
b10101111 +
0&
#1796246
0,
1"
b10000 $
b10000 0
b11 3
1&
#1814764
b11111111 4
b0 (
b0 +
0)
0&
#1833282
1&
#1851800
1)
b11111111 (
b11111111 +
0&
#1870318
1&
#1888836
b0 (
b0 +
0)
0&
#1907354
1&
#1925872
1*
1%
0&
#1944390
0"
b1111 $
b1111 0
b100 2
b10100000 !
b10100000 1
1&
#1962908
0*
0%
0&
#1981426
1&
#1999944
1*
1%
0&
#2018462
b1110 $
b1110 0
b101 2
b10100001 !
b10100001 1
1&
#2036980
0*
0%
0&
#2055498
1&
#2074016
1*
1%
0&
#2092534
b1101 $
b1101 0
b110 2
b10100010 !
b10100010 1
1&
#2111052
0*
0%
0&
#2129570
1&
#2148088
1*
1%
0&
#2166606
b1100 $
b1100 0
b111 2
b10100011 !
b10100011 1
1&
#2185124
0*
0%
0&
#2203642
1&
#2222160
1*
1,
1%
1)
b1010101 (
b1010101 +
0&
#2240678
b1000 2
b10100100 !
b10100100 1
b100 3
1&
#2259196
0*
0,
b0 (
b0 +
0%
0)
0&
