16_MacUnit/macUnit/src/macUnit.sv
// Fixed-Point Multiply-Accumulate
// accumulator = accumulator + (a * b)

module macUnit (
    input logic sys_clk,
    input logic sys_rst_n,

    input logic clear,
    input logic inputValid,
    input logic signed [7:0] a,
    input logic signed [7:0] b,

    output logic outputValid,
    output logic signed [15:0] accumulator // 16 bits so accumulator has more room for storage
);

    logic signed [15:0] rawProduct;
    logic signed [15:0] scaledProduct;

    assign rawProduct = a * b;
    assign scaledProduct = rawProduct >>> 4;

    always_ff @(posedge sys_clk or negedge sys_rst_n) begin
        if (!sys_rst_n) begin
            accumulator <= 16'sd0;
            outputValid <= 1'b0;
        end else begin
            outputValid <= 1'b0;    // Default, no new accumulated output this cycle
        
            if (clear) begin        // Clear has priority over accumulation
                accumulator <= 16'sd0;
            end else if (inputValid) begin
                accumulator <= accumulator + scaledProduct;
                outputValid <= 1'b1;
            end
        end
     end

endmodule

Verilog/16_MacUnit/sim/tb_macUnit.sv
`timescale 1ns/1ps

module tb_macUnit;
    
    logic sys_clk;
    logic sys_rst_n;

    logic clear;
    logic inputValid;
    logic signed [7:0] a;
    logic signed [7:0] b;

    logic outputValid;
    logic signed [15:0] accumulator;

    macUnit dut (
        .sys_clk(sys_clk),
        .sys_rst_n(sys_rst_n),
        .clear(clear),
        .inputValid(inputValid),
        .a(a),
        .b(b),
        .outputValid(outputValid),
        .accumulator(accumulator)
);

    initial begin
        sys_clk = 1'b0;
        forever #18.518 sys_clk = ~sys_clk; // 27 MHz clock
    end

    
    // One MAC operation per clock cyle
    // Inputs change on falling edge for stability, DUT samples them on the next rising edge
    task sendMac(
        input logic signed [7:0] inputA,
        input logic signed [7:0] inputB
    );
        begin
            @(negedge sys_clk);
            a = inputA;
            b = inputB;
            inputValid = 1'b1;

            @(negedge sys_clk);
            inputValid = 1'b0;
            a = 8'sd0;
            b = 8'sd0;
        end
    endtask

    task clearAccumulator;
        begin
            @(negedge sys_clk);
            clear = 1'b1;

            @(negedge sys_clk);
            clear = 1'b0;
        end
    endtask

    initial begin
        $dumpfile("sim/tb_macUnit.vcd");
        $dumpvars(0, tb_macUnit);
        
        sys_rst_n = 1'b0;
        clear = 1'b0;
        inputValid = 1'b0;
        a = 8'sd0;
        b = 8'sd0;

        #200;
        sys_rst_n = 1'b1;

        // 1.0 * 2.0 = 2.0
        // 0.5 * 2.0 = 1.0
        // 1.5 * 2.0 = 3.0
        // Final sum: 2.0 + 1.0 + 3.0 = 6.0
        // Q4.4 stored: 6.0 * 16 = 96 = 16'sh0060
        sendMac(8'sh10, 8'sh20);
        sendMac(8'sh08, 8'sh20);
        sendMac(8'sh18, 8'sh20);

        clearAccumulator();

        // -1.0 * 2.0 = -2.0
        // 0.5  * 2.0 =  1.0
        // Final sum: -1.0
        // Q4.4 stored: -1.0 * 16 = -16 = 16'shFFF0
        sendMac(8'shF0, 8'sh20);
        sendMac(8'sh08, 8'sh20);

        repeat (4) @(posedge sys_clk);

        $finish;
    end

endmodule

16_MacUnit/sim/tb_macUnit.vcd
$date
	Tue Jul  7 14:25:11 2026
$end
$version
	Icarus Verilog
$end
$timescale
	1ps
$end
$scope module tb_macUnit $end
$var wire 1 ! outputValid $end
$var wire 16 " accumulator [15:0] $end
$var reg 8 # a [7:0] $end
$var reg 8 $ b [7:0] $end
$var reg 1 % clear $end
$var reg 1 & inputValid $end
$var reg 1 ' sys_clk $end
$var reg 1 ( sys_rst_n $end
$scope module dut $end
$var wire 8 ) a [7:0] $end
$var wire 8 * b [7:0] $end
$var wire 1 % clear $end
$var wire 1 & inputValid $end
$var wire 1 ' sys_clk $end
$var wire 1 ( sys_rst_n $end
$var wire 16 + scaledProduct [15:0] $end
$var wire 16 , rawProduct [15:0] $end
$var reg 16 - accumulator [15:0] $end
$var reg 1 ! outputValid $end
$upscope $end
$scope task clearAccumulator $end
$upscope $end
$scope task sendMac $end
$var reg 8 . inputA [7:0] $end
$var reg 8 / inputB [7:0] $end
$upscope $end
$upscope $end
$enddefinitions $end
$comment Show the parameter values. $end
$dumpall
$end
#0
$dumpvars
bx /
bx .
b0 -
b0 ,
b0 +
b0 *
b0 )
0(
0'
0&
0%
b0 $
b0 #
b0 "
0!
$end
#18518
1'
#37036
0'
#55554
1'
#74072
0'
#92590
1'
#111108
0'
#129626
1'
#148144
0'
#166662
1'
#185180
0'
#200000
b100000 /
b10000 .
1(
#203698
1'
#222216
b100000 +
1&
b1000000000 ,
b100000 $
b100000 *
b10000 #
b10000 )
0'
#240734
1!
b100000 "
b100000 -
1'
#259252
b0 +
b1000 .
b0 $
b0 *
b0 ,
b0 #
b0 )
0&
0'
#277770
0!
1'
#296288
b10000 +
1&
b100000000 ,
b100000 $
b100000 *
b1000 #
b1000 )
0'
#314806
1!
b110000 "
b110000 -
1'
#333324
b0 +
b11000 .
b0 $
b0 *
b0 ,
b0 #
b0 )
0&
0'
#351842
0!
1'
#370360
b110000 +
1&
b1100000000 ,
b100000 $
b100000 *
b11000 #
b11000 )
0'
#388878
1!
b1100000 "
b1100000 -
1'
#407396
b0 +
b0 $
b0 *
b0 ,
b0 #
b0 )
0&
0'
#425914
0!
1'
#444432
1%
0'
#462950
b0 "
b0 -
1'
#481468
b11110000 .
0%
0'
#499986
1'
#518504
b1111111111100000 +
1&
b1111111000000000 ,
b100000 $
b100000 *
b11110000 #
b11110000 )
0'
#537022
1!
b1111111111100000 "
b1111111111100000 -
1'
#555540
b0 +
b1000 .
b0 $
b0 *
b0 ,
b0 #
b0 )
0&
0'
#574058
0!
1'
#592576
b10000 +
1&
b100000000 ,
b100000 $
b100000 *
b1000 #
b1000 )
0'
#611094
1!
b1111111111110000 "
b1111111111110000 -
1'
#629612
b0 +
b0 $
b0 *
b0 ,
b0 #
b0 )
0&
0'
#648130
0!
1'
