20_AsyncFifo/asyncFifo/src/asyncFifo.sv
// Safely pass data from one clock domain to another.
// Do not directly pass multi-bit binary counters across clock domains.
// Instead: binary pointer -> Gray-code pointer -> two-flop synchronizer -> compare
// Gray Code: Only one bit changes at a time. This reduces ambiguity when the other clock domain samples the pointer.

module asyncFifo #(
    parameter int DATA_WIDTH = 8,
    parameter int ADDR_WIDTH = 4
) (
    input logic writeClk,
    input logic writeRst_n,
    input logic writeEnable,
    input logic [DATA_WIDTH-1:0] writeData,
    output logic full,

    input logic readClk,
    input logic readRst_n,
    input logic readEnable,
    output logic [DATA_WIDTH-1:0] readData,
    output logic empty
);

    localparam int DEPTH = 1 << ADDR_WIDTH; // Memory Depth = 2^ADDR_WIDTH = 16
    logic [DATA_WIDTH-1:0] memory [0:DEPTH-1];

    // Binary pointers are used locally for addressing memory
    // ADDR_WIDTH + 1, extra MSB distinguishes full from empty
    logic [ADDR_WIDTH:0] writeBinary;
    logic [ADDR_WIDTH:0] writeBinaryNext;
    logic [ADDR_WIDTH:0] readBinary;
    logic [ADDR_WIDTH:0] readBinaryNext;

    // Gray-code pointers are used for clock-domain crossing
    logic [ADDR_WIDTH:0] writeGray;
    logic [ADDR_WIDTH:0] writeGrayNext;
    logic [ADDR_WIDTH:0] readGray;
    logic [ADDR_WIDTH:0] readGrayNext;

    // Synchronized pointers crossing into the opposite clock domain
    logic [ADDR_WIDTH:0] readGrayWriteClk1;
    logic [ADDR_WIDTH:0] readGrayWriteClk2;
    logic [ADDR_WIDTH:0] writeGrayReadClk1;
    logic [ADDR_WIDTH:0] writeGrayReadClk2;

    logic writeValid;
    logic readValid;
    logic fullNext;
    logic emptyNext;

    assign writeValid = writeEnable && !full;
    assign readValid = readEnable && !empty;

    function automatic logic [ADDR_WIDTH:0] binaryToGray(input logic [ADDR_WIDTH:0] binaryValue);
        begin
            binaryToGray = binaryValue ^ (binaryValue >> 1);  // Binary to Gray-code conversion formula
            // "^" is bitwise XOR
        end
    endfunction

    // Local Next pointers
    assign writeBinaryNext = writeBinary + writeValid;
    assign readBinaryNext = readBinary + readValid;

    assign writeGrayNext = binaryToGray(writeBinaryNext);
    assign readGrayNext = binaryToGray(readBinaryNext);

    // Full detection
    // FIFO is full when advancing the write pointer would make it equal to
    // the read pointer with the two most-significant Gray-code bits inverted.
    assign fullNext = (writeGrayNext == {~readGrayWriteClk2[ADDR_WIDTH:ADDR_WIDTH-1],readGrayWriteClk2[ADDR_WIDTH-2:0]});

    // Empty detection.
    // FIFO is empty when the next read pointer equals the synchronized write pointer.
    assign emptyNext = (readGrayNext == writeGrayReadClk2);

    // Write clock domain.
    always_ff @(posedge writeClk or negedge writeRst_n) begin
        if (!writeRst_n) begin
            writeBinary <= '0;
            writeGray <= '0;

            readGrayWriteClk1 <= '0;
            readGrayWriteClk2 <= '0;

            full <= 1'b0;
        end else begin
            // Synchronize read pointer into write clock domain.
            readGrayWriteClk1 <= readGray;
            readGrayWriteClk2 <= readGrayWriteClk1;

            // Write data only when FIFO is not full.
            if (writeValid) begin
                memory[writeBinary[ADDR_WIDTH-1:0]] <= writeData;
                writeBinary <= writeBinaryNext;
                writeGray <= writeGrayNext;
            end

            full <= fullNext;
        end
    end

    // Read clock domain.
    always_ff @(posedge readClk or negedge readRst_n) begin
        if (!readRst_n) begin
            readBinary <= '0;
            readGray <= '0;

            writeGrayReadClk1 <= '0;
            writeGrayReadClk2 <= '0;

            readData <= '0;
            empty <= 1'b1;
        end else begin
            // Synchronize write pointer into read clock domain.
            writeGrayReadClk1 <= writeGray;
            writeGrayReadClk2 <= writeGrayReadClk1;

            // Read data only when FIFO is not empty.
            if (readValid) begin
                readData <= memory[readBinary[ADDR_WIDTH-1:0]];
                readBinary <= readBinaryNext;
                readGray <= readGrayNext;
            end

            empty <= emptyNext;
        end
    end

endmodule

20_AsyncFifo/sim/tb_asyncFifo.sv
`timescale 1ns/1ps

module tb_asyncFifo;

    logic writeClk;
    logic writeRst_n;
    logic writeEnable;
    logic [7:0] writeData;
    logic full;

    logic readClk;
    logic readRst_n;
    logic readEnable;
    logic [7:0] readData;
    logic empty;

    int errorCount;

    asyncFifo dut (
        .writeClk(writeClk),
        .writeRst_n(writeRst_n),
        .writeEnable(writeEnable),
        .writeData(writeData),
        .full(full),

        .readClk(readClk),
        .readRst_n(readRst_n),
        .readEnable(readEnable),
        .readData(readData),
        .empty(empty)
    );

    initial begin
        writeClk = 1'b0;
        forever #10 writeClk = ~writeClk; // 50 MHz write clock
    end

    initial begin
        readClk = 1'b0;
        forever #17 readClk = ~readClk; // Different read clock
    end

    // Write one byte into the FIFO
    // This task waits while full is high
    // A write transfer happens on writeClk when: writeEnable && !full
    task writeByte(input logic [7:0] dataByte);
        begin
            @(negedge writeClk);

            while (full) begin
                @(negedge writeClk);
            end

            writeData = dataByte;
            writeEnable = 1'b1;

            @(negedge writeClk);
            writeEnable = 1'b0;
            writeData = 8'd0;
        end
    endtask

    // Read one byte and compare it against the expected value
    // This task waits while empty is high
    // A read transfer happens on readClk when: readEnable && !empty
    task readByteExpect(input logic [7:0] expectedByte);
        begin
            @(negedge readClk);

            while (empty) begin
                @(negedge readClk);
            end

            readEnable = 1'b1;

            @(posedge readClk);
            #1;

            if (readData !== expectedByte) begin
                $display("ERROR: expected %02h, got %02h at time %0t", expectedByte, readData, $time);
                errorCount = errorCount + 1;
            end else begin
                $display("PASS: read %02h at time %0t", readData, $time);
            end

            @(negedge readClk);
            readEnable = 1'b0;
        end
    endtask

    initial begin
        $dumpfile("sim/tb_asyncFifo.vcd");
        $dumpvars(0, tb_asyncFifo);

        writeRst_n = 1'b0;
        readRst_n = 1'b0;

        writeEnable = 1'b0;
        writeData = 8'd0;

        readEnable = 1'b0;

        errorCount = 0;

        #200;

        writeRst_n = 1'b1;
        readRst_n = 1'b1;

        // Give synchronizers time to settle after reset
        repeat (5) @(posedge writeClk);
        repeat (5) @(posedge readClk);

        // Basic order test.
        // FIFO must preserve order: A1, B2, C3, D4
        fork
            begin
                writeByte(8'hA1);
                writeByte(8'hB2);
                writeByte(8'hC3);
                writeByte(8'hD4);
            end

            begin
                readByteExpect(8'hA1);
                readByteExpect(8'hB2);
                readByteExpect(8'hC3);
                readByteExpect(8'hD4);
            end
        join

        // Fill-pressure test
        // Write many values before reading
        // This exercises pointer wrap and full/empty behavior
        fork
            begin
                writeByte(8'h10);
                writeByte(8'h11);
                writeByte(8'h12);
                writeByte(8'h13);
                writeByte(8'h14);
                writeByte(8'h15);
                writeByte(8'h16);
                writeByte(8'h17);
                writeByte(8'h18);
                writeByte(8'h19);
                writeByte(8'h1A);
                writeByte(8'h1B);
                writeByte(8'h1C);
                writeByte(8'h1D);
                writeByte(8'h1E);
                writeByte(8'h1F);
            end

            begin
                // Delay reads so FIFO fills first.
                repeat (20) @(posedge readClk);

                readByteExpect(8'h10);
                readByteExpect(8'h11);
                readByteExpect(8'h12);
                readByteExpect(8'h13);
                readByteExpect(8'h14);
                readByteExpect(8'h15);
                readByteExpect(8'h16);
                readByteExpect(8'h17);
                readByteExpect(8'h18);
                readByteExpect(8'h19);
                readByteExpect(8'h1A);
                readByteExpect(8'h1B);
                readByteExpect(8'h1C);
                readByteExpect(8'h1D);
                readByteExpect(8'h1E);
                readByteExpect(8'h1F);
            end
        join

        repeat (10) @(posedge readClk);

        if (errorCount == 0) begin
            $display("ASYNC FIFO TEST PASSED");
        end else begin
            $display("ASYNC FIFO TEST FAILED with %0d error(s)", errorCount);
        end

        $finish;
    end

endmodule

20_AsyncFifo/sim/tb_asyncFifo.vcd
$date
	Tue Jul  7 20:44:31 2026
$end
$version
	Icarus Verilog
$end
$timescale
	1ps
$end
$scope module tb_asyncFifo $end
$var wire 8 ! readData [7:0] $end
$var wire 1 " full $end
$var wire 1 # empty $end
$var reg 1 $ readClk $end
$var reg 1 % readEnable $end
$var reg 1 & readRst_n $end
$var reg 1 ' writeClk $end
$var reg 8 ( writeData [7:0] $end
$var reg 1 ) writeEnable $end
$var reg 1 * writeRst_n $end
$var integer 32 + errorCount [31:0] $end
$scope module dut $end
$var wire 1 $ readClk $end
$var wire 1 % readEnable $end
$var wire 1 & readRst_n $end
$var wire 1 , readValid $end
$var wire 1 ' writeClk $end
$var wire 8 - writeData [7:0] $end
$var wire 1 ) writeEnable $end
$var wire 1 * writeRst_n $end
$var wire 1 . writeValid $end
$var wire 5 / writeGrayNext [4:0] $end
$var wire 5 0 writeBinaryNext [4:0] $end
$var wire 5 1 readGrayNext [4:0] $end
$var wire 5 2 readBinaryNext [4:0] $end
$var wire 1 3 fullNext $end
$var wire 1 4 emptyNext $end
$var parameter 32 5 ADDR_WIDTH $end
$var parameter 32 6 DATA_WIDTH $end
$var parameter 32 7 DEPTH $end
$var reg 1 # empty $end
$var reg 1 " full $end
$var reg 5 8 readBinary [4:0] $end
$var reg 8 9 readData [7:0] $end
$var reg 5 : readGray [4:0] $end
$var reg 5 ; readGrayWriteClk1 [4:0] $end
$var reg 5 < readGrayWriteClk2 [4:0] $end
$var reg 5 = writeBinary [4:0] $end
$var reg 5 > writeGray [4:0] $end
$var reg 5 ? writeGrayReadClk1 [4:0] $end
$var reg 5 @ writeGrayReadClk2 [4:0] $end
$scope function binaryToGray $end
$upscope $end
$upscope $end
$scope task readByteExpect $end
$var reg 8 A expectedByte [7:0] $end
$upscope $end
$scope task writeByte $end
$var reg 8 B dataByte [7:0] $end
$upscope $end
$upscope $end
$enddefinitions $end
$comment Show the parameter values. $end
$dumpall
b10000 7
b1000 6
b100 5
$end
#0
$dumpvars
bx B
bx A
b0 @
b0 ?
b0 >
b0 =
b0 <
b0 ;
b0 :
b0 9
b0 8
14
03
b0 2
b0 1
b0 0
b0 /
0.
b0 -
0,
b0 +
0*
0)
b0 (
0'
0&
0%
0$
1#
0"
b0 !
$end
#10000
1'
#17000
1$
#20000
0'
#30000
1'
#34000
0$
#40000
0'
#50000
1'
#51000
1$
#60000
0'
#68000
0$
#70000
1'
#80000
0'
#85000
1$
#90000
1'
#100000
0'
#102000
0$
#110000
1'
#119000
1$
#120000
0'
#130000
1'
#136000
0$
#140000
0'
#150000
1'
#153000
1$
#160000
0'
#170000
1'
0$
#180000
0'
#187000
1$
#190000
1'
#200000
0'
1&
1*
#204000
0$
#210000
1'
#220000
0'
#221000
1$
#230000
1'
#238000
0$
#240000
0'
#250000
1'
#255000
1$
#260000
0'
#270000
1'
#272000
0$
#280000
0'
#289000
1$
#290000
1'
#300000
0'
#306000
0$
#310000
1'
#320000
0'
#323000
1$
#330000
1'
#340000
0'
0$
#350000
1'
#357000
1$
#360000
0'
#370000
1'
#374000
0$
#380000
0'
#390000
1'
#391000
1$
#400000
0'
#408000
0$
#410000
1'
#420000
0'
#425000
1$
#430000
1'
#440000
0'
#442000
0$
#450000
1'
#459000
b10100001 B
b10100001 A
1$
#460000
b1 /
b1 0
1.
1)
b10100001 (
b10100001 -
0'
#470000
b11 /
b1 >
b10 0
b1 =
1'
#476000
0$
#480000
b1 /
b1 0
0.
b10110010 B
b0 (
b0 -
0)
0'
#490000
1'
#493000
b1 ?
1$
#500000
b11 /
b10 0
1.
1)
b10110010 (
b10110010 -
0'
#510000
b10 /
b11 >
b11 0
b10 =
1'
0$
#520000
b11 /
b10 0
0.
b11000011 B
b0 (
b0 -
0)
0'
#527000
04
b1 @
b11 ?
1$
#530000
1'
#540000
b10 /
b11 0
1.
1)
b11000011 (
b11000011 -
0'
#544000
0$
#550000
b110 /
b10 >
b100 0
b11 =
1'
#560000
b10 /
b11 0
0.
b11010100 B
b0 (
b0 -
0)
0'
#561000
0#
b11 @
b10 ?
1$
#570000
1'
#578000
b1 1
b1 2
1,
1%
0$
#580000
b110 /
b100 0
1.
1)
b11010100 (
b11010100 -
0'
#590000
b111 /
b110 >
b101 0
b100 =
1'
#595000
b11 1
b1 :
b10 2
b1 8
b10100001 !
b10100001 9
b10 @
b110 ?
1$
#600000
b110 /
b100 0
0.
b0 (
b0 -
0)
0'
#610000
b1 ;
1'
#612000
b1 1
b1 2
0,
b10110010 A
0%
0$
#620000
0'
#629000
b110 @
1$
#630000
b1 <
1'
#640000
0'
#646000
b11 1
b10 2
1,
1%
0$
#650000
1'
#660000
0'
#663000
b10 1
b11 :
b11 2
b10 8
b10110010 !
b10110010 9
1$
#670000
b11 ;
1'
#680000
b11 1
b10 2
0,
b11000011 A
0%
0'
0$
#690000
b11 <
1'
#697000
1$
#700000
0'
#710000
1'
#714000
b10 1
b11 2
1,
1%
0$
#720000
0'
#730000
1'
#731000
14
b110 1
b10 :
b100 2
b11 8
b11000011 !
b11000011 9
1$
#740000
0'
#748000
04
b10 1
b11 2
0,
b11010100 A
0%
0$
#750000
b10 ;
1'
#760000
0'
#765000
1$
#770000
b10 <
1'
#780000
0'
#782000
14
b110 1
b100 2
1,
1%
0$
#790000
1'
#799000
0,
14
b110 1
1#
b110 :
b100 2
b100 8
b11010100 !
b11010100 9
1$
#800000
0'
#810000
b110 ;
1'
#816000
b10000 B
0%
0$
#820000
b111 /
b101 0
1.
1)
b10000 (
b10000 -
0'
#830000
b101 /
b111 >
b110 0
b101 =
b110 <
1'
#833000
b111 ?
1$
#840000
b111 /
b101 0
0.
b10001 B
b0 (
b0 -
0)
0'
#850000
1'
0$
#860000
b101 /
b110 0
1.
1)
b10001 (
b10001 -
0'
#867000
04
b111 @
1$
#870000
b100 /
b101 >
b111 0
b110 =
1'
#880000
b101 /
b110 0
0.
b10010 B
b0 (
b0 -
0)
0'
#884000
0$
#890000
1'
#900000
b100 /
b111 0
1.
1)
b10010 (
b10010 -
0'
#901000
0#
b101 ?
1$
#910000
b1100 /
b100 >
b1000 0
b111 =
1'
#918000
0$
#920000
b100 /
b111 0
0.
b10011 B
b0 (
b0 -
0)
0'
#930000
1'
#935000
b101 @
b100 ?
1$
#940000
b1100 /
b1000 0
1.
1)
b10011 (
b10011 -
0'
#950000
b1101 /
b1100 >
b1001 0
b1000 =
1'
#952000
0$
#960000
b1100 /
b1000 0
0.
b10100 B
b0 (
b0 -
0)
0'
#969000
b100 @
b1100 ?
1$
#970000
1'
#980000
b1101 /
b1001 0
1.
1)
b10100 (
b10100 -
0'
#986000
0$
#990000
b1111 /
b1101 >
b1010 0
b1001 =
1'
#1000000
b1101 /
b1001 0
0.
b10101 B
b0 (
b0 -
0)
0'
#1003000
b1100 @
b1101 ?
1$
#1010000
1'
#1020000
b1111 /
b1010 0
1.
1)
b10101 (
b10101 -
0'
0$
#1030000
b1110 /
b1111 >
b1011 0
b1010 =
1'
#1037000
b1101 @
b1111 ?
1$
#1040000
b1111 /
b1010 0
0.
b10110 B
b0 (
b0 -
0)
0'
#1050000
1'
#1054000
0$
#1060000
b1110 /
b1011 0
1.
1)
b10110 (
b10110 -
0'
#1070000
b1010 /
b1110 >
b1100 0
b1011 =
1'
#1071000
b1111 @
b1110 ?
1$
#1080000
b1110 /
b1011 0
0.
b10111 B
b0 (
b0 -
0)
0'
#1088000
0$
#1090000
1'
#1100000
b1010 /
b1100 0
1.
1)
b10111 (
b10111 -
0'
#1105000
b1110 @
1$
#1110000
b1011 /
b1010 >
b1101 0
b1100 =
1'
#1120000
b1010 /
b1100 0
0.
b11000 B
b0 (
b0 -
0)
0'
#1122000
0$
#1130000
1'
#1139000
b1010 ?
1$
#1140000
b1011 /
b1101 0
1.
1)
b11000 (
b11000 -
0'
#1150000
b1001 /
b1011 >
b1110 0
b1101 =
1'
#1156000
0$
#1160000
b1011 /
b1101 0
0.
b11001 B
b0 (
b0 -
0)
0'
#1170000
1'
#1173000
b1010 @
b1011 ?
1$
#1180000
b1001 /
b1110 0
1.
1)
b11001 (
b11001 -
0'
#1190000
b1000 /
b1001 >
b1111 0
b1110 =
1'
0$
#1200000
b1001 /
b1110 0
0.
b11010 B
b0 (
b0 -
0)
0'
#1207000
b1011 @
b1001 ?
1$
#1210000
1'
#1220000
b1000 /
b1111 0
1.
1)
b11010 (
b11010 -
0'
#1224000
0$
#1230000
b11000 /
b1000 >
b10000 0
b1111 =
1'
#1240000
b1000 /
b1111 0
0.
b11011 B
b0 (
b0 -
0)
0'
#1241000
b1001 @
b1000 ?
1$
#1250000
1'
#1258000
0$
#1260000
b11000 /
b10000 0
1.
1)
b11011 (
b11011 -
0'
#1270000
b11001 /
b11000 >
b10001 0
b10000 =
1'
#1275000
b1000 @
b11000 ?
1$
#1280000
b11000 /
b10000 0
0.
b11100 B
b0 (
b0 -
0)
0'
#1290000
1'
#1292000
0$
#1300000
b11001 /
b10001 0
1.
1)
b11100 (
b11100 -
0'
#1309000
b11000 @
1$
#1310000
b11011 /
b11001 >
b10010 0
b10001 =
1'
#1320000
b11001 /
b10001 0
0.
b11101 B
b0 (
b0 -
0)
0'
#1326000
0$
#1330000
1'
#1340000
b11011 /
b10010 0
1.
1)
b11101 (
b11101 -
0'
#1343000
b11001 ?
1$
#1350000
b11010 /
b11011 >
b10011 0
b10010 =
1'
#1360000
b11011 /
b10010 0
0.
b11110 B
b0 (
b0 -
0)
0'
0$
#1370000
1'
#1377000
b11001 @
b11011 ?
1$
#1380000
b11010 /
b10011 0
1.
1)
b11110 (
b11110 -
0'
#1390000
13
b11110 /
b11010 >
b10100 0
b10011 =
1'
#1394000
0$
#1400000
03
b11010 /
b10011 0
0.
b11111 B
b0 (
b0 -
0)
0'
#1410000
1'
#1411000
b11011 @
b11010 ?
1$
#1420000
13
b11110 /
b10100 0
1.
1)
b11111 (
b11111 -
0'
#1428000
0$
#1430000
0.
13
b11110 /
1"
b11110 >
b10100 0
b10100 =
1'
#1440000
b0 (
b0 -
0)
0'
#1445000
b11010 @
b11110 ?
1$
#1450000
1'
#1460000
0'
#1462000
0$
#1470000
1'
#1479000
b11110 @
b10000 A
1$
#1480000
0'
#1490000
1'
#1496000
b111 1
b101 2
1,
1%
0$
#1500000
0'
#1510000
1'
#1513000
b101 1
b111 :
b110 2
b101 8
b10000 !
b10000 9
1$
#1520000
0'
#1530000
b111 ;
b111 1
b101 2
0,
b10001 A
0%
1'
0$
#1540000
0'
#1547000
1$
#1550000
03
b111 <
1'
#1560000
0'
#1564000
b101 1
b110 2
1,
1%
0$
#1570000
0"
1'
#1580000
0'
#1581000
b100 1
b101 :
b111 2
b110 8
b10001 !
b10001 9
1$
#1590000
b101 ;
1'
#1598000
b101 1
b110 2
0,
b10010 A
0%
0$
#1600000
0'
#1610000
b101 <
1'
#1615000
1$
#1620000
0'
#1630000
1'
#1632000
b100 1
b111 2
1,
1%
0$
#1640000
0'
#1649000
b1100 1
b100 :
b1000 2
b111 8
b10010 !
b10010 9
1$
#1650000
b100 ;
1'
#1660000
0'
#1666000
b100 1
b111 2
0,
b10011 A
0%
0$
#1670000
b100 <
1'
#1680000
0'
#1683000
1$
#1690000
1'
#1700000
b1100 1
b1000 2
1,
1%
0'
0$
#1710000
1'
#1717000
b1101 1
b1100 :
b1001 2
b1000 8
b10011 !
b10011 9
1$
#1720000
0'
#1730000
b1100 ;
1'
#1734000
b1100 1
b1000 2
0,
b10100 A
0%
0$
#1740000
0'
#1750000
b1100 <
1'
#1751000
1$
#1760000
0'
#1768000
b1101 1
b1001 2
1,
1%
0$
#1770000
1'
#1780000
0'
#1785000
b1111 1
b1101 :
b1010 2
b1001 8
b10100 !
b10100 9
1$
#1790000
b1101 ;
1'
#1800000
0'
#1802000
b1101 1
b1001 2
0,
b10101 A
0%
0$
#1810000
b1101 <
1'
#1819000
1$
#1820000
0'
#1830000
1'
#1836000
b1111 1
b1010 2
1,
1%
0$
#1840000
0'
#1850000
1'
#1853000
b1110 1
b1111 :
b1011 2
b1010 8
b10101 !
b10101 9
1$
#1860000
0'
#1870000
b1111 ;
b1111 1
b1010 2
0,
b10110 A
0%
1'
0$
#1880000
0'
#1887000
1$
#1890000
b1111 <
1'
#1900000
0'
#1904000
b1110 1
b1011 2
1,
1%
0$
#1910000
1'
#1920000
0'
#1921000
b1010 1
b1110 :
b1100 2
b1011 8
b10110 !
b10110 9
1$
#1930000
b1110 ;
1'
#1938000
b1110 1
b1011 2
0,
b10111 A
0%
0$
#1940000
0'
#1950000
b1110 <
1'
#1955000
1$
#1960000
0'
#1970000
1'
#1972000
b1010 1
b1100 2
1,
1%
0$
#1980000
0'
#1989000
b1011 1
b1010 :
b1101 2
b1100 8
b10111 !
b10111 9
1$
#1990000
b1010 ;
1'
#2000000
0'
#2006000
b1010 1
b1100 2
0,
b11000 A
0%
0$
#2010000
b1010 <
1'
#2020000
0'
#2023000
1$
#2030000
1'
#2040000
b1011 1
b1101 2
1,
1%
0'
0$
#2050000
1'
#2057000
b1001 1
b1011 :
b1110 2
b1101 8
b11000 !
b11000 9
1$
#2060000
0'
#2070000
b1011 ;
1'
#2074000
b1011 1
b1101 2
0,
b11001 A
0%
0$
#2080000
0'
#2090000
b1011 <
1'
#2091000
1$
#2100000
0'
#2108000
b1001 1
b1110 2
1,
1%
0$
#2110000
1'
#2120000
0'
#2125000
b1000 1
b1001 :
b1111 2
b1110 8
b11001 !
b11001 9
1$
#2130000
b1001 ;
1'
#2140000
0'
#2142000
b1001 1
b1110 2
0,
b11010 A
0%
0$
#2150000
b1001 <
1'
#2159000
1$
#2160000
0'
#2170000
1'
#2176000
b1000 1
b1111 2
1,
1%
0$
#2180000
0'
#2190000
1'
#2193000
b11000 1
b1000 :
b10000 2
b1111 8
b11010 !
b11010 9
1$
#2200000
0'
#2210000
b1000 ;
b1000 1
b1111 2
0,
b11011 A
0%
1'
0$
#2220000
0'
#2227000
1$
#2230000
b1000 <
1'
#2240000
0'
#2244000
b11000 1
b10000 2
1,
1%
0$
#2250000
1'
#2260000
0'
#2261000
b11001 1
b11000 :
b10001 2
b10000 8
b11011 !
b11011 9
1$
#2270000
b11000 ;
1'
#2278000
b11000 1
b10000 2
0,
b11100 A
0%
0$
#2280000
0'
#2290000
b11000 <
1'
#2295000
1$
#2300000
0'
#2310000
1'
#2312000
b11001 1
b10001 2
1,
1%
0$
#2320000
0'
#2329000
b11011 1
b11001 :
b10010 2
b10001 8
b11100 !
b11100 9
1$
#2330000
b11001 ;
1'
#2340000
0'
#2346000
b11001 1
b10001 2
0,
b11101 A
0%
0$
#2350000
b11001 <
1'
#2360000
0'
#2363000
1$
#2370000
1'
#2380000
b11011 1
b10010 2
1,
1%
0'
0$
#2390000
1'
#2397000
b11010 1
b11011 :
b10011 2
b10010 8
b11101 !
b11101 9
1$
#2400000
0'
#2410000
b11011 ;
1'
#2414000
b11011 1
b10010 2
0,
b11110 A
0%
0$
#2420000
0'
#2430000
b11011 <
1'
#2431000
1$
#2440000
0'
#2448000
b11010 1
b10011 2
1,
1%
0$
#2450000
1'
#2460000
0'
#2465000
14
b11110 1
b11010 :
b10100 2
b10011 8
b11110 !
b11110 9
1$
#2470000
b11010 ;
1'
#2480000
0'
#2482000
04
b11010 1
b10011 2
0,
b11111 A
0%
0$
#2490000
b11010 <
1'
#2499000
1$
#2500000
0'
#2510000
1'
#2516000
14
b11110 1
b10100 2
1,
1%
0$
#2520000
0'
#2530000
1'
#2533000
0,
14
b11110 1
1#
b11110 :
b10100 2
b10100 8
b11111 !
b11111 9
1$
#2540000
0'
#2550000
b11110 ;
0%
1'
0$
#2560000
0'
#2567000
1$
#2570000
b11110 <
1'
